{"tops": {"baidu": {"tops": [{"rank": 1, "name": "从六中全会公报看世界第一大党", "count": "4978482", "link": "https://www.baidu.com/s?wd=%E4%BB%8E%E5%85%AD%E4%B8%AD%E5%85%A8%E4%BC%9A%E5%85%AC%E6%8A%A5%E7%9C%8B%E4%B8%96%E7%95%8C%E7%AC%AC%E4%B8%80%E5%A4%A7%E5%85%9A&rsv_dl=fyb_news"}, {"rank": 2, "name": "金球奖颁奖一览:莱万获最佳前锋", "count": "4821553", "link": "https://www.baidu.com/s?wd=%E9%87%91%E7%90%83%E5%A5%96%E9%A2%81%E5%A5%96%E4%B8%80%E8%A7%88%3A%E8%8E%B1%E4%B8%87%E8%8E%B7%E6%9C%80%E4%BD%B3%E5%89%8D%E9%94%8B&rsv_dl=fyb_news"}, {"rank": 3, "name": "十九届六中全会决议中的10个明确", "count": "4788936", "link": "https://www.baidu.com/s?wd=%E5%8D%81%E4%B9%9D%E5%B1%8A%E5%85%AD%E4%B8%AD%E5%85%A8%E4%BC%9A%E5%86%B3%E8%AE%AE%E4%B8%AD%E7%9A%8410%E4%B8%AA%E6%98%8E%E7%A1%AE&rsv_dl=fyb_news"}, {"rank": 4, "name": "孙颖莎王曼昱世乒赛女双夺冠", "count": "4606498", "link": "https://www.baidu.com/s?wd=%E5%AD%99%E9%A2%96%E8%8E%8E%E7%8E%8B%E6%9B%BC%E6%98%B1%E4%B8%96%E4%B9%92%E8%B5%9B%E5%A5%B3%E5%8F%8C%E5%A4%BA%E5%86%A0&rsv_dl=fyb_news"}, {"rank": 5, "name": "梅西第七次获得金球奖", "count": "4516403", "link": "https://www.baidu.com/s?wd=%23%E6%A2%85%E8%A5%BF%E7%AC%AC%E4%B8%83%E6%AC%A1%E8%8E%B7%E9%87%91%E7%90%83%E5%A5%96%23&rsv_dl=fyb_news"}, {"rank": 6, "name": "今冬第四轮大范围寒潮来了", "count": "4492772", "link": "https://www.baidu.com/s?wd=%E4%BB%8A%E5%86%AC%E7%AC%AC%E5%9B%9B%E8%BD%AE%E5%A4%A7%E8%8C%83%E5%9B%B4%E5%AF%92%E6%BD%AE%E6%9D%A5%E4%BA%86&rsv_dl=fyb_news"}, {"rank": 7, "name": "河南多地凌晨突然被不明物体照亮", "count": "4347755", "link": "https://www.baidu.com/s?wd=%E6%B2%B3%E5%8D%97%E5%A4%9A%E5%9C%B0%E5%87%8C%E6%99%A8%E7%AA%81%E7%84%B6%E8%A2%AB%E4%B8%8D%E6%98%8E%E7%89%A9%E4%BD%93%E7%85%A7%E4%BA%AE&rsv_dl=fyb_news"}, {"rank": 8, "name": "专家称现有疫苗对奥密克戎仍有效", "count": "4230221", "link": "https://www.baidu.com/s?wd=%E4%B8%93%E5%AE%B6%E7%A7%B0%E7%8E%B0%E6%9C%89%E7%96%AB%E8%8B%97%E5%AF%B9%E5%A5%A5%E5%AF%86%E5%85%8B%E6%88%8E%E4%BB%8D%E6%9C%89%E6%95%88&rsv_dl=fyb_news"}, {"rank": 9, "name": "微信试行松绑外链", "count": "4130896", "link": "https://www.baidu.com/s?wd=%E5%BE%AE%E4%BF%A1%E8%AF%95%E8%A1%8C%E6%9D%BE%E7%BB%91%E5%A4%96%E9%93%BE&rsv_dl=fyb_news"}, {"rank": 10, "name": "国乒大魔王张怡宁夸赞小魔王", "count": "4016948", "link": "https://www.baidu.com/s?wd=%E5%9B%BD%E4%B9%92%E5%A4%A7%E9%AD%94%E7%8E%8B%E5%BC%A0%E6%80%A1%E5%AE%81%E5%A4%B8%E8%B5%9E%E5%B0%8F%E9%AD%94%E7%8E%8B&rsv_dl=fyb_news"}, {"rank": 11, "name": "王岳伦宣布与李湘离婚后又删除", "count": "3934654", "link": "https://www.baidu.com/s?wd=%E7%8E%8B%E5%B2%B3%E4%BC%A6%E5%AE%A3%E5%B8%83%E4%B8%8E%E6%9D%8E%E6%B9%98%E7%A6%BB%E5%A9%9A%E5%90%8E%E5%8F%88%E5%88%A0%E9%99%A4&rsv_dl=fyb_news"}, {"rank": 12, "name": "奥密克戎传染力比德尔塔增37.5%", "count": "3805985", "link": "https://www.baidu.com/s?wd=%E5%A5%A5%E5%AF%86%E5%85%8B%E6%88%8E%E4%BC%A0%E6%9F%93%E5%8A%9B%E6%AF%94%E5%BE%B7%E5%B0%94%E5%A1%94%E5%A2%9E37.5%25&rsv_dl=fyb_news"}, {"rank": 13, "name": "中国从未邀请美国政客出席冬奥会", "count": "3742619", "link": "https://www.baidu.com/s?wd=%E4%B8%AD%E5%9B%BD%E4%BB%8E%E6%9C%AA%E9%82%80%E8%AF%B7%E7%BE%8E%E5%9B%BD%E6%94%BF%E5%AE%A2%E5%87%BA%E5%B8%AD%E5%86%AC%E5%A5%A5%E4%BC%9A&rsv_dl=fyb_news"}, {"rank": 14, "name": "广州一高校20多人发烧腹泻被隔离", "count": "3611723", "link": "https://www.baidu.com/s?wd=%E5%B9%BF%E5%B7%9E%E4%B8%80%E9%AB%98%E6%A0%A120%E5%A4%9A%E4%BA%BA%E5%8F%91%E7%83%A7%E8%85%B9%E6%B3%BB%E8%A2%AB%E9%9A%94%E7%A6%BB&rsv_dl=fyb_news"}, {"rank": 15, "name": "孙颖莎夺世乒赛第二金", "count": "3528422", "link": "https://www.baidu.com/s?wd=%E5%AD%99%E9%A2%96%E8%8E%8E%E5%A4%BA%E4%B8%96%E4%B9%92%E8%B5%9B%E7%AC%AC%E4%BA%8C%E9%87%91&rsv_dl=fyb_news"}, {"rank": 16, "name": "关于奥密克戎 卫健委权威解答来了", "count": "3499948", "link": "https://www.baidu.com/s?wd=%E5%85%B3%E4%BA%8E%E5%A5%A5%E5%AF%86%E5%85%8B%E6%88%8E+%E5%8D%AB%E5%81%A5%E5%A7%94%E6%9D%83%E5%A8%81%E8%A7%A3%E7%AD%94%E6%9D%A5%E4%BA%86&rsv_dl=fyb_news"}, {"rank": 17, "name": "实探越狱犯朱贤健被抓捕现场", "count": "3383418", "link": "https://www.baidu.com/s?wd=%E5%AE%9E%E6%8E%A2%E8%B6%8A%E7%8B%B1%E7%8A%AF%E6%9C%B1%E8%B4%A4%E5%81%A5%E8%A2%AB%E6%8A%93%E6%8D%95%E7%8E%B0%E5%9C%BA&rsv_dl=fyb_news"}, {"rank": 18, "name": "赌王洗米华的博彩江湖和资本布局", "count": "3264965", "link": "https://www.baidu.com/s?wd=%E8%B5%8C%E7%8E%8B%E6%B4%97%E7%B1%B3%E5%8D%8E%E7%9A%84%E5%8D%9A%E5%BD%A9%E6%B1%9F%E6%B9%96%E5%92%8C%E8%B5%84%E6%9C%AC%E5%B8%83%E5%B1%80&rsv_dl=fyb_news"}, {"rank": 19, "name": "中国将再向非方提供10亿剂疫苗", "count": "3195084", "link": "https://www.baidu.com/s?wd=%E4%B8%AD%E5%9B%BD%E5%B0%86%E5%86%8D%E5%90%91%E9%9D%9E%E6%96%B9%E6%8F%90%E4%BE%9B10%E4%BA%BF%E5%89%82%E7%96%AB%E8%8B%97&rsv_dl=fyb_news"}, {"rank": 20, "name": "内蒙古新巴尔虎右旗2人核酸阳性", "count": "3069276", "link": "https://www.baidu.com/s?wd=%E5%86%85%E8%92%99%E5%8F%A4%E6%96%B0%E5%B7%B4%E5%B0%94%E8%99%8E%E5%8F%B3%E6%97%972%E4%BA%BA%E6%A0%B8%E9%85%B8%E9%98%B3%E6%80%A7&rsv_dl=fyb_news"}, {"rank": 21, "name": "内蒙古满洲里检出阳性样本60份", "count": "2997286", "link": "https://www.baidu.com/s?wd=%E5%86%85%E8%92%99%E5%8F%A4%E6%BB%A1%E6%B4%B2%E9%87%8C%E6%A3%80%E5%87%BA%E9%98%B3%E6%80%A7%E6%A0%B7%E6%9C%AC60%E4%BB%BD&rsv_dl=fyb_news"}, {"rank": 22, "name": "金鸡奖提名名单公布", "count": "2895823", "link": "https://www.baidu.com/s?wd=%E9%87%91%E9%B8%A1%E5%A5%96%E6%8F%90%E5%90%8D%E5%90%8D%E5%8D%95%E5%85%AC%E5%B8%83&rsv_dl=fyb_news"}, {"rank": 23, "name": "王岳伦删除对李湘表白帖", "count": "2711134", "link": "https://www.baidu.com/s?wd=%E7%8E%8B%E5%B2%B3%E4%BC%A6%E5%88%A0%E9%99%A4%E5%AF%B9%E6%9D%8E%E6%B9%98%E8%A1%A8%E7%99%BD%E5%B8%96&rsv_dl=fyb_news"}, {"rank": 24, "name": "警方海滩发现失联摄影师风衣手机", "count": "2699132", "link": "https://www.baidu.com/s?wd=%E8%AD%A6%E6%96%B9%E6%B5%B7%E6%BB%A9%E5%8F%91%E7%8E%B0%E5%A4%B1%E8%81%94%E6%91%84%E5%BD%B1%E5%B8%88%E9%A3%8E%E8%A1%A3%E6%89%8B%E6%9C%BA&rsv_dl=fyb_news"}, {"rank": 25, "name": "洗米华被送监狱羁押 警方荷枪实弹", "count": "2510298", "link": "https://www.baidu.com/s?wd=%E6%B4%97%E7%B1%B3%E5%8D%8E%E8%A2%AB%E9%80%81%E7%9B%91%E7%8B%B1%E7%BE%81%E6%8A%BC+%E8%AD%A6%E6%96%B9%E8%8D%B7%E6%9E%AA%E5%AE%9E%E5%BC%B9&rsv_dl=fyb_news"}, {"rank": 26, "name": "国乒混双组合横扫日本夺冠", "count": "2435041", "link": "https://www.baidu.com/s?wd=%E5%9B%BD%E4%B9%92%E6%B7%B7%E5%8F%8C%E7%BB%84%E5%90%88%E6%A8%AA%E6%89%AB%E6%97%A5%E6%9C%AC%E5%A4%BA%E5%86%A0&rsv_dl=fyb_news"}, {"rank": 27, "name": "康辉错过母亲最后一面在飞机上落泪", "count": "2319911", "link": "https://www.baidu.com/s?wd=%E5%BA%B7%E8%BE%89%E9%94%99%E8%BF%87%E6%AF%8D%E4%BA%B2%E6%9C%80%E5%90%8E%E4%B8%80%E9%9D%A2%E5%9C%A8%E9%A3%9E%E6%9C%BA%E4%B8%8A%E8%90%BD%E6%B3%AA&rsv_dl=fyb_news"}, {"rank": 28, "name": "深圳警方通报一男子路口劫持人质", "count": "2204701", "link": "https://www.baidu.com/s?wd=%E6%B7%B1%E5%9C%B3%E8%AD%A6%E6%96%B9%E9%80%9A%E6%8A%A5%E4%B8%80%E7%94%B7%E5%AD%90%E8%B7%AF%E5%8F%A3%E5%8A%AB%E6%8C%81%E4%BA%BA%E8%B4%A8&rsv_dl=fyb_news"}, {"rank": 29, "name": "日本将禁止所有海外旅客入境", "count": "2106761", "link": "https://www.baidu.com/s?wd=%E6%97%A5%E6%9C%AC%E5%B0%86%E7%A6%81%E6%AD%A2%E6%89%80%E6%9C%89%E6%B5%B7%E5%A4%96%E6%97%85%E5%AE%A2%E5%85%A5%E5%A2%83&rsv_dl=fyb_news"}, {"rank": 30, "name": "美军侦察机罕见穿越台湾海峡", "count": "2036875", "link": "https://www.baidu.com/s?wd=%E7%BE%8E%E5%86%9B%E4%BE%A6%E5%AF%9F%E6%9C%BA%E7%BD%95%E8%A7%81%E7%A9%BF%E8%B6%8A%E5%8F%B0%E6%B9%BE%E6%B5%B7%E5%B3%A1&rsv_dl=fyb_news"}], "name": "百度热搜"}, "douyin": {"tops": [{"rank": "1", "name": "河南多地深夜拍到不明物体坠落", "count": "1079.2万", "link": "https://www.douyin.com/search/河南多地深夜拍到不明物体坠落?source=normal_search&enter_from=recommend"}, {"rank": "2", "name": "钟南山对奥密克戎做出最新研判", "count": "957.1万", "link": "https://www.douyin.com/search/钟南山对奥密克戎做出最新研判?source=normal_search&enter_from=recommend"}, {"rank": "3", "name": "十九届六中全会知识点", "count": "954.5万", "link": "https://www.douyin.com/search/十九届六中全会知识点?source=normal_search&enter_from=recommend"}, {"rank": "4", "name": "大学生为了做视频有多努力", "count": "942.2万", "link": "https://www.douyin.com/search/大学生为了做视频有多努力?source=normal_search&enter_from=recommend"}, {"rank": "5", "name": "梅西第七次获得金球奖", "count": "927.7万", "link": "https://www.douyin.com/search/梅西第七次获得金球奖?source=normal_search&enter_from=recommend"}, {"rank": "6", "name": "原来蔓越莓是这样收的", "count": "910.8万", "link": "https://www.douyin.com/search/原来蔓越莓是这样收的?source=normal_search&enter_from=recommend"}, {"rank": "7", "name": "2021金球奖", "count": "906.0万", "link": "https://www.douyin.com/search/2021金球奖?source=normal_search&enter_from=recommend"}, {"rank": "8", "name": "王曼昱孙颖莎世乒赛女双夺冠", "count": "889.7万", "link": "https://www.douyin.com/search/王曼昱孙颖莎世乒赛女双夺冠?source=normal_search&enter_from=recommend"}, {"rank": "9", "name": "教师法拟规定教师资格相应学历学位", "count": "873.9万", "link": "https://www.douyin.com/search/教师法拟规定教师资格相应学历学位?source=normal_search&enter_from=recommend"}, {"rank": "10", "name": "林俊杰演唱会收益全部捐赠", "count": "867.8万", "link": "https://www.douyin.com/search/林俊杰演唱会收益全部捐赠?source=normal_search&enter_from=recommend"}, {"rank": "11", "name": "被女心理师职场老好人整破防了", "count": "866.7万", "link": "https://www.douyin.com/search/被女心理师职场老好人整破防了?source=normal_search&enter_from=recommend"}, {"rank": "12", "name": "顾月霜结局意难平", "count": "861.0万", "link": "https://www.douyin.com/search/顾月霜结局意难平?source=normal_search&enter_from=recommend"}, {"rank": "13", "name": "白敬亭不玩光剑变装的原因", "count": "856.0万", "link": "https://www.douyin.com/search/白敬亭不玩光剑变装的原因?source=normal_search&enter_from=recommend"}, {"rank": "14", "name": "内蒙古满洲里检出阳性样本60份", "count": "854.3万", "link": "https://www.douyin.com/search/内蒙古满洲里检出阳性样本60份?source=normal_search&enter_from=recommend"}, {"rank": "15", "name": "大学上课发现老师是商界大佬", "count": "852.8万", "link": "https://www.douyin.com/search/大学上课发现老师是商界大佬?source=normal_search&enter_from=recommend"}, {"rank": "16", "name": "唐梓准备退网生孩子", "count": "834.7万", "link": "https://www.douyin.com/search/唐梓准备退网生孩子?source=normal_search&enter_from=recommend"}, {"rank": "17", "name": "玲娜贝儿的反差萌", "count": "832.5万", "link": "https://www.douyin.com/search/玲娜贝儿的反差萌?source=normal_search&enter_from=recommend"}, {"rank": "18", "name": "女子欲让老人在展厅坐便器上排便", "count": "829.8万", "link": "https://www.douyin.com/search/女子欲让老人在展厅坐便器上排便?source=normal_search&enter_from=recommend"}, {"rank": "19", "name": "东北人日常偶遇野生东北虎", "count": "826.4万", "link": "https://www.douyin.com/search/东北人日常偶遇野生东北虎?source=normal_search&enter_from=recommend"}, {"rank": "20", "name": "近亲结婚的危害有多大", "count": "825.1万", "link": "https://www.douyin.com/search/近亲结婚的危害有多大?source=normal_search&enter_from=recommend"}, {"rank": "21", "name": "女艺人们的光剑变装来了", "count": "823.6万", "link": "https://www.douyin.com/search/女艺人们的光剑变装来了?source=normal_search&enter_from=recommend"}, {"rank": "22", "name": "目击者回应深夜拍到不明物体坠落", "count": "809.4万", "link": "https://www.douyin.com/search/目击者回应深夜拍到不明物体坠落?source=normal_search&enter_from=recommend"}, {"rank": "23", "name": "我是咪咪", "count": "797.0万", "link": "https://www.douyin.com/search/我是咪咪?source=normal_search&enter_from=recommend"}, {"rank": "24", "name": "曝李铁涉嫌用国脚资格置换利益", "count": "795.5万", "link": "https://www.douyin.com/search/曝李铁涉嫌用国脚资格置换利益?source=normal_search&enter_from=recommend"}, {"rank": "25", "name": "超10国确诊奥密克戎新冠变异株", "count": "788.3万", "link": "https://www.douyin.com/search/超10国确诊奥密克戎新冠变异株?source=normal_search&enter_from=recommend"}, {"rank": "26", "name": "欧洲6国出现奥密克戎病例", "count": "786.1万", "link": "https://www.douyin.com/search/欧洲6国出现奥密克戎病例?source=normal_search&enter_from=recommend"}, {"rank": "27", "name": "黛玉葬花新解", "count": "783.5万", "link": "https://www.douyin.com/search/黛玉葬花新解?source=normal_search&enter_from=recommend"}, {"rank": "28", "name": "先生请出山舞蹈教学", "count": "773.4万", "link": "https://www.douyin.com/search/先生请出山舞蹈教学?source=normal_search&enter_from=recommend"}, {"rank": "29", "name": "蓝桉已遇释槐鸟是什么梗", "count": "771.1万", "link": "https://www.douyin.com/search/蓝桉已遇释槐鸟是什么梗?source=normal_search&enter_from=recommend"}, {"rank": "30", "name": "影视达人在评论区团建了", "count": "760.8万", "link": "https://www.douyin.com/search/影视达人在评论区团建了?source=normal_search&enter_from=recommend"}, {"rank": "31", "name": "2021演技封神榜", "count": "744.6万", "link": "https://www.douyin.com/search/2021演技封神榜?source=normal_search&enter_from=recommend"}, {"rank": "32", "name": "中国从未邀请美国政客出席冬奥", "count": "743.2万", "link": "https://www.douyin.com/search/中国从未邀请美国政客出席冬奥?source=normal_search&enter_from=recommend"}, {"rank": "33", "name": "来海南感受深夜赶海的快乐", "count": "742.8万", "link": "https://www.douyin.com/search/来海南感受深夜赶海的快乐?source=normal_search&enter_from=recommend"}, {"rank": "34", "name": "女子误以为自己中了20万手舞足蹈", "count": "723.2万", "link": "https://www.douyin.com/search/女子误以为自己中了20万手舞足蹈?source=normal_search&enter_from=recommend"}, {"rank": "35", "name": "25岁摄影师发遗书后失联", "count": "719.1万", "link": "https://www.douyin.com/search/25岁摄影师发遗书后失联?source=normal_search&enter_from=recommend"}, {"rank": "36", "name": "十根烤肠的仪式感让阿姨很忙", "count": "718.5万", "link": "https://www.douyin.com/search/十根烤肠的仪式感让阿姨很忙?source=normal_search&enter_from=recommend"}, {"rank": "37", "name": "象腿男孩正从截肢手术中恢复", "count": "713.4万", "link": "https://www.douyin.com/search/象腿男孩正从截肢手术中恢复?source=normal_search&enter_from=recommend"}, {"rank": "38", "name": "圣诞摇铃变装", "count": "700.9万", "link": "https://www.douyin.com/search/圣诞摇铃变装?source=normal_search&enter_from=recommend"}, {"rank": "39", "name": "林俊杰再唱可惜没如果", "count": "696.9万", "link": "https://www.douyin.com/search/林俊杰再唱可惜没如果?source=normal_search&enter_from=recommend"}, {"rank": "40", "name": "投诉外卖也能逆向思维", "count": "692.5万", "link": "https://www.douyin.com/search/投诉外卖也能逆向思维?source=normal_search&enter_from=recommend"}, {"rank": "41", "name": "长大后才读懂记承天寺夜游", "count": "690.6万", "link": "https://www.douyin.com/search/长大后才读懂记承天寺夜游?source=normal_search&enter_from=recommend"}, {"rank": "42", "name": "八旬奶奶拍视频诉说孤独", "count": "687.7万", "link": "https://www.douyin.com/search/八旬奶奶拍视频诉说孤独?source=normal_search&enter_from=recommend"}, {"rank": "43", "name": "爸爸接女儿接了个寂寞", "count": "680.3万", "link": "https://www.douyin.com/search/爸爸接女儿接了个寂寞?source=normal_search&enter_from=recommend"}, {"rank": "44", "name": "景区回应网红为拍视频堵桥", "count": "672.3万", "link": "https://www.douyin.com/search/景区回应网红为拍视频堵桥?source=normal_search&enter_from=recommend"}, {"rank": "45", "name": "在张同学评论区恶补剧情", "count": "669.1万", "link": "https://www.douyin.com/search/在张同学评论区恶补剧情?source=normal_search&enter_from=recommend"}, {"rank": "46", "name": "官方回应公务员女子殴打年迈母亲", "count": "659.8万", "link": "https://www.douyin.com/search/官方回应公务员女子殴打年迈母亲?source=normal_search&enter_from=recommend"}, {"rank": "47", "name": "大司马献唱宣传片主题曲芜湖起飞", "count": "657.0万", "link": "https://www.douyin.com/search/大司马献唱宣传片主题曲芜湖起飞?source=normal_search&enter_from=recommend"}, {"rank": "48", "name": "大一和大四的穿搭对比", "count": "651.4万", "link": "https://www.douyin.com/search/大一和大四的穿搭对比?source=normal_search&enter_from=recommend"}, {"rank": "49", "name": "徒手剥生鸡蛋挑战", "count": "632.3万", "link": "https://www.douyin.com/search/徒手剥生鸡蛋挑战?source=normal_search&enter_from=recommend"}, {"rank": "50", "name": "女子讨要工资卡不成殴打年迈母亲", "count": "628.3万", "link": "https://www.douyin.com/search/女子讨要工资卡不成殴打年迈母亲?source=normal_search&enter_from=recommend"}], "name": "抖音热搜"}, "toutiao": {"tops": [{"rank": "1", "name": "人民日报八论六中全会", "count": "622.1万", "link": "https://so.toutiao.com/search?dvpf=pc&source=sug&keyword=人民日报八论六中全会"}, {"rank": "2", "name": "全党要牢记1个根本问题", "count": "509.3万", "link": "https://so.toutiao.com/search?dvpf=pc&source=sug&keyword=全党要牢记1个根本问题"}, {"rank": "3", "name": "孙颖莎王曼昱横扫日本组合夺冠", "count": "460.9万", "link": "https://so.toutiao.com/search?dvpf=pc&source=sug&keyword=孙颖莎王曼昱横扫日本组合夺冠"}, {"rank": "4", "name": "梅西第七次获得金球奖", "count": "417.0万", "link": "https://so.toutiao.com/search?dvpf=pc&source=sug&keyword=梅西第七次获得金球奖"}, {"rank": "5", "name": "奥密克戎毒株20天扩散至超10国", "count": "377.3万", "link": "https://so.toutiao.com/search?dvpf=pc&source=sug&keyword=奥密克戎毒株20天扩散至超10国"}, {"rank": "6", "name": "全球日增确诊近50万例", "count": "252.9万", "link": "https://so.toutiao.com/search?dvpf=pc&source=sug&keyword=全球日增确诊近50万例"}, {"rank": "7", "name": "校长游戏花3千万 氪金游戏问题在哪", "count": "228.9万", "link": "https://so.toutiao.com/search?dvpf=pc&source=sug&keyword=校长游戏花3千万 氪金游戏问题在哪"}, {"rank": "8", "name": "河南多地深夜拍到流星坠落", "count": "207.1万", "link": "https://so.toutiao.com/search?dvpf=pc&source=sug&keyword=河南多地深夜拍到流星坠落"}, {"rank": "9", "name": "洪都拉斯左翼候选人宣布赢得大选", "count": "187.4万", "link": "https://so.toutiao.com/search?dvpf=pc&source=sug&keyword=洪都拉斯左翼候选人宣布赢得大选"}, {"rank": "10", "name": "中国已针对奥密克戎建立特异核检", "count": "169.5万", "link": "https://so.toutiao.com/search?dvpf=pc&source=sug&keyword=中国已针对奥密克戎建立特异核检"}, {"rank": "11", "name": "经济学家回应12岁儿子坠亡", "count": "341.4万", "link": "https://so.toutiao.com/search?dvpf=pc&source=sug&keyword=经济学家回应12岁儿子坠亡"}, {"rank": "12", "name": "河南一交警副支队长遭前妻实名举报", "count": "308.9万", "link": "https://so.toutiao.com/search?dvpf=pc&source=sug&keyword=河南一交警副支队长遭前妻实名举报"}, {"rank": "13", "name": "金球奖颁奖一览：莱万获得最佳前锋", "count": "279.5万", "link": "https://so.toutiao.com/search?dvpf=pc&source=sug&keyword=金球奖颁奖一览：莱万获得最佳前锋"}, {"rank": "14", "name": "福奇：“奥密克戎”传入美国不奇怪", "count": "125.6万", "link": "https://so.toutiao.com/search?dvpf=pc&source=sug&keyword=福奇：“奥密克戎”传入美国不奇怪"}, {"rank": "15", "name": "王东峰当选河北省委书记", "count": "113.6万", "link": "https://so.toutiao.com/search?dvpf=pc&source=sug&keyword=王东峰当选河北省委书记"}, {"rank": "16", "name": "澳女子不满隔离纵火烧隔离酒店", "count": "102.8万", "link": "https://so.toutiao.com/search?dvpf=pc&source=sug&keyword=澳女子不满隔离纵火烧隔离酒店"}, {"rank": "17", "name": "上海试点部分地区应届研究生落户", "count": "93.0万", "link": "https://so.toutiao.com/search?dvpf=pc&source=sug&keyword=上海试点部分地区应届研究生落户"}, {"rank": "18", "name": "教师法修订草案征求意见稿发布", "count": "76.2万", "link": "https://so.toutiao.com/search?dvpf=pc&source=sug&keyword=教师法修订草案征求意见稿发布"}, {"rank": "19", "name": "官网战力榜：勇士太阳篮网位居三甲", "count": "62.4万", "link": "https://so.toutiao.com/search?dvpf=pc&source=sug&keyword=官网战力榜：勇士太阳篮网位居三甲"}, {"rank": "20", "name": "教师准入学历门槛拟大幅提升", "count": "51.1万", "link": "https://so.toutiao.com/search?dvpf=pc&source=sug&keyword=教师准入学历门槛拟大幅提升"}, {"rank": "21", "name": "王岳伦官宣与李湘离婚后秒删", "count": "562.9万", "link": "https://so.toutiao.com/search?dvpf=pc&source=sug&keyword=王岳伦官宣与李湘离婚后秒删"}, {"rank": "22", "name": "金鸡奖提名影片你最喜欢哪一部", "count": "84.2万", "link": "https://so.toutiao.com/search?dvpf=pc&source=sug&keyword=金鸡奖提名影片你最喜欢哪一部"}, {"rank": "23", "name": "媒体评论：洗米华的结局早已注定", "count": "68.9万", "link": "https://so.toutiao.com/search?dvpf=pc&source=sug&keyword=媒体评论：洗米华的结局早已注定"}, {"rank": "24", "name": "奥密克戎传染力比德尔塔增加37.5%", "count": "46.2万", "link": "https://so.toutiao.com/search?dvpf=pc&source=sug&keyword=奥密克戎传染力比德尔塔增加37.5%"}, {"rank": "25", "name": "赵心童逆转希金斯进英国锦标赛16强", "count": "153.4万", "link": "https://so.toutiao.com/search?dvpf=pc&source=sug&keyword=赵心童逆转希金斯进英国锦标赛16强"}, {"rank": "26", "name": "《我的姐姐》获金鸡奖六项提名", "count": "41.8万", "link": "https://so.toutiao.com/search?dvpf=pc&source=sug&keyword=《我的姐姐》获金鸡奖六项提名"}, {"rank": "27", "name": "12月起一批新法规将陆续施行", "count": "37.8万", "link": "https://so.toutiao.com/search?dvpf=pc&source=sug&keyword=12月起一批新法规将陆续施行"}, {"rank": "28", "name": "刘宁当选广西壮族自治区党委书记", "count": "34.2万", "link": "https://so.toutiao.com/search?dvpf=pc&source=sug&keyword=刘宁当选广西壮族自治区党委书记"}, {"rank": "29", "name": "格里芬掉出轮转后联系小乔丹寻帮助", "count": "138.8万", "link": "https://so.toutiao.com/search?dvpf=pc&source=sug&keyword=格里芬掉出轮转后联系小乔丹寻帮助"}, {"rank": "30", "name": "古天乐林峯出演郑保瑞新片", "count": "31.0万", "link": "https://so.toutiao.com/search?dvpf=pc&source=sug&keyword=古天乐林峯出演郑保瑞新片"}, {"rank": "31", "name": "著名播音艺术家方明逝世", "count": "28.0万", "link": "https://so.toutiao.com/search?dvpf=pc&source=sug&keyword=著名播音艺术家方明逝世"}, {"rank": "32", "name": "广汽集团子公司广汽埃安资产重组", "count": "25.4万", "link": "https://so.toutiao.com/search?dvpf=pc&source=sug&keyword=广汽集团子公司广汽埃安资产重组"}, {"rank": "33", "name": "尼克斯主帅：沃克掉出球队轮转", "count": "56.4万", "link": "https://so.toutiao.com/search?dvpf=pc&source=sug&keyword=尼克斯主帅：沃克掉出球队轮转"}, {"rank": "34", "name": "今冬第4轮寒潮来袭", "count": "22.9万", "link": "https://so.toutiao.com/search?dvpf=pc&source=sug&keyword=今冬第4轮寒潮来袭"}, {"rank": "35", "name": "历届金鸡奖评选出了哪些黄金配角", "count": "20.8万", "link": "https://so.toutiao.com/search?dvpf=pc&source=sug&keyword=历届金鸡奖评选出了哪些黄金配角"}, {"rank": "36", "name": "满洲里17感染者住同一小区", "count": "18.8万", "link": "https://so.toutiao.com/search?dvpf=pc&source=sug&keyword=满洲里17感染者住同一小区"}, {"rank": "37", "name": "新西兰将启用疫情防控新体系", "count": "17.0万", "link": "https://so.toutiao.com/search?dvpf=pc&source=sug&keyword=新西兰将启用疫情防控新体系"}, {"rank": "38", "name": "realme新旗舰命名GT2 Pro", "count": "15.4万", "link": "https://so.toutiao.com/search?dvpf=pc&source=sug&keyword=realme新旗舰命名GT2 Pro"}, {"rank": "39", "name": "无臂乡村教师代课村小18年", "count": "13.9万", "link": "https://so.toutiao.com/search?dvpf=pc&source=sug&keyword=无臂乡村教师代课村小18年"}, {"rank": "40", "name": "南非未来几周或迎第四波疫情", "count": "12.6万", "link": "https://so.toutiao.com/search?dvpf=pc&source=sug&keyword=南非未来几周或迎第四波疫情"}, {"rank": "41", "name": "西南交大男生进女卫生间偷拍被退学", "count": "11.4万", "link": "https://so.toutiao.com/search?dvpf=pc&source=sug&keyword=西南交大男生进女卫生间偷拍被退学"}, {"rank": "42", "name": "51岁周杰深夜带美女聚餐被拍", "count": "10.3万", "link": "https://so.toutiao.com/search?dvpf=pc&source=sug&keyword=51岁周杰深夜带美女聚餐被拍"}, {"rank": "43", "name": "贵阳招重量级科技人才最高奖1亿", "count": "9.3万", "link": "https://so.toutiao.com/search?dvpf=pc&source=sug&keyword=贵阳招重量级科技人才最高奖1亿"}, {"rank": "44", "name": "中国拟建立教师荣誉表彰制度", "count": "8.4万", "link": "https://so.toutiao.com/search?dvpf=pc&source=sug&keyword=中国拟建立教师荣誉表彰制度"}, {"rank": "45", "name": "江宏杰谈离婚后状态", "count": "7.6万", "link": "https://so.toutiao.com/search?dvpf=pc&source=sug&keyword=江宏杰谈离婚后状态"}, {"rank": "46", "name": "博纳称与太阳娱乐项目均在正常范畴", "count": "6.9万", "link": "https://so.toutiao.com/search?dvpf=pc&source=sug&keyword=博纳称与太阳娱乐项目均在正常范畴"}, {"rank": "47", "name": "学者称两岸关系处于“转型阶段”", "count": "6.3万", "link": "https://so.toutiao.com/search?dvpf=pc&source=sug&keyword=学者称两岸关系处于“转型阶段”"}, {"rank": "48", "name": "靳东老婆晒照为儿子庆生", "count": "5.7万", "link": "https://so.toutiao.com/search?dvpf=pc&source=sug&keyword=靳东老婆晒照为儿子庆生"}, {"rank": "49", "name": "男子自购半斤牛肉拍照给商家好评", "count": "5.1万", "link": "https://so.toutiao.com/search?dvpf=pc&source=sug&keyword=男子自购半斤牛肉拍照给商家好评"}, {"rank": "50", "name": "格里芬谈掉出轮换：会保持职业态度", "count": "4.6万", "link": "https://so.toutiao.com/search?dvpf=pc&source=sug&keyword=格里芬谈掉出轮换：会保持职业态度"}], "name": "头条热搜"}, "weibo_search": {"tops": [{"rank": "1", "name": "儿媳怀孕婆婆送来90斤肉150个土鸡蛋 ", "count": "2318872", "link": "https://s.weibo.com//weibo?q=%23%E5%84%BF%E5%AA%B3%E6%80%80%E5%AD%95%E5%A9%86%E5%A9%86%E9%80%81%E6%9D%A590%E6%96%A4%E8%82%89150%E4%B8%AA%E5%9C%9F%E9%B8%A1%E8%9B%8B%23&Refer=top"}, {"rank": "2", "name": "王曼昱孙颖莎世乒赛女双夺冠 ", "count": "1250553", "link": "https://s.weibo.com//weibo?q=%23%E7%8E%8B%E6%9B%BC%E6%98%B1%E5%AD%99%E9%A2%96%E8%8E%8E%E4%B8%96%E4%B9%92%E8%B5%9B%E5%A5%B3%E5%8F%8C%E5%A4%BA%E5%86%A0%23&Refer=top"}, {"rank": "3", "name": "全党要牢记1个根本问题 ", "count": "1208236", "link": "https://s.weibo.com//weibo?q=%23%E5%85%A8%E5%85%9A%E8%A6%81%E7%89%A2%E8%AE%B01%E4%B8%AA%E6%A0%B9%E6%9C%AC%E9%97%AE%E9%A2%98%23&Refer=top"}, {"rank": "•", "name": "总裁在剧本杀当NPC ", "count": "", "link": "https://s.weibo.com//weibo?q=%23%E6%80%BB%E8%A3%81%E5%9C%A8%E5%89%A7%E6%9C%AC%E6%9D%80%E5%BD%93NPC%23&topic_ad=1&Refer=top"}, {"rank": "4", "name": "欧阳娜娜在藏族婚礼上当伴娘 ", "count": "1207316", "link": "https://s.weibo.com//weibo?q=%23%E6%AC%A7%E9%98%B3%E5%A8%9C%E5%A8%9C%E5%9C%A8%E8%97%8F%E6%97%8F%E5%A9%9A%E7%A4%BC%E4%B8%8A%E5%BD%93%E4%BC%B4%E5%A8%98%23&Refer=top"}, {"rank": "5", "name": "帝旭终于知道海市是女儿身了 ", "count": "1205419", "link": "https://s.weibo.com//weibo?q=%23%E5%B8%9D%E6%97%AD%E7%BB%88%E4%BA%8E%E7%9F%A5%E9%81%93%E6%B5%B7%E5%B8%82%E6%98%AF%E5%A5%B3%E5%84%BF%E8%BA%AB%E4%BA%86%23&Refer=top"}, {"rank": "6", "name": "快递员送雪碧上楼猛晃箱子 ", "count": "1017279", "link": "https://s.weibo.com//weibo?q=%23%E5%BF%AB%E9%80%92%E5%91%98%E9%80%81%E9%9B%AA%E7%A2%A7%E4%B8%8A%E6%A5%BC%E7%8C%9B%E6%99%83%E7%AE%B1%E5%AD%90%23&Refer=top"}, {"rank": "7", "name": "不希望易烊千玺四字成为束缚 ", "count": "990469", "link": "https://s.weibo.com//weibo?q=%23%E4%B8%8D%E5%B8%8C%E6%9C%9B%E6%98%93%E7%83%8A%E5%8D%83%E7%8E%BA%E5%9B%9B%E5%AD%97%E6%88%90%E4%B8%BA%E6%9D%9F%E7%BC%9A%23&Refer=top"}, {"rank": "8", "name": "央视网揭秘网红店营销套路 ", "count": "874927", "link": "https://s.weibo.com//weibo?q=%23%E5%A4%AE%E8%A7%86%E7%BD%91%E6%8F%AD%E7%A7%98%E7%BD%91%E7%BA%A2%E5%BA%97%E8%90%A5%E9%94%80%E5%A5%97%E8%B7%AF%23&Refer=top"}, {"rank": "9", "name": "逃犯戏弄他人女友被打后报警 ", "count": "793741", "link": "https://s.weibo.com//weibo?q=%23%E9%80%83%E7%8A%AF%E6%88%8F%E5%BC%84%E4%BB%96%E4%BA%BA%E5%A5%B3%E5%8F%8B%E8%A2%AB%E6%89%93%E5%90%8E%E6%8A%A5%E8%AD%A6%23&Refer=top"}, {"rank": "10", "name": "梅西第七次获得金球奖 ", "count": "693813", "link": "https://s.weibo.com//weibo?q=%23%E6%A2%85%E8%A5%BF%E7%AC%AC%E4%B8%83%E6%AC%A1%E8%8E%B7%E5%BE%97%E9%87%91%E7%90%83%E5%A5%96%23&Refer=top"}, {"rank": "11", "name": "当家主母的猫入驻微博 ", "count": "671288", "link": "https://s.weibo.com//weibo?q=%23%E5%BD%93%E5%AE%B6%E4%B8%BB%E6%AF%8D%E7%9A%84%E7%8C%AB%E5%85%A5%E9%A9%BB%E5%BE%AE%E5%8D%9A%23&Refer=top"}, {"rank": "12", "name": "胡歌看女心理师认不出菅纫姿 ", "count": "666799", "link": "https://s.weibo.com//weibo?q=%23%E8%83%A1%E6%AD%8C%E7%9C%8B%E5%A5%B3%E5%BF%83%E7%90%86%E5%B8%88%E8%AE%A4%E4%B8%8D%E5%87%BA%E8%8F%85%E7%BA%AB%E5%A7%BF%23&Refer=top"}, {"rank": "13", "name": "千百惠高调晒出大陆身份证 ", "count": "648957", "link": "https://s.weibo.com//weibo?q=%23%E5%8D%83%E7%99%BE%E6%83%A0%E9%AB%98%E8%B0%83%E6%99%92%E5%87%BA%E5%A4%A7%E9%99%86%E8%BA%AB%E4%BB%BD%E8%AF%81%23&Refer=top"}, {"rank": "14", "name": "奶奶用老鼠熬油治孩子烫伤致感染 ", "count": "617123", "link": "https://s.weibo.com//weibo?q=%23%E5%A5%B6%E5%A5%B6%E7%94%A8%E8%80%81%E9%BC%A0%E7%86%AC%E6%B2%B9%E6%B2%BB%E5%AD%A9%E5%AD%90%E7%83%AB%E4%BC%A4%E8%87%B4%E6%84%9F%E6%9F%93%23&Refer=top"}, {"rank": "15", "name": "原来烤红薯还能这么吃 ", "count": "589885", "link": "https://s.weibo.com//weibo?q=%23%E5%8E%9F%E6%9D%A5%E7%83%A4%E7%BA%A2%E8%96%AF%E8%BF%98%E8%83%BD%E8%BF%99%E4%B9%88%E5%90%83%23&Refer=top"}, {"rank": "16", "name": "女子半夜醒来从床缝捡起老公 ", "count": "579323", "link": "https://s.weibo.com//weibo?q=%23%E5%A5%B3%E5%AD%90%E5%8D%8A%E5%A4%9C%E9%86%92%E6%9D%A5%E4%BB%8E%E5%BA%8A%E7%BC%9D%E6%8D%A1%E8%B5%B7%E8%80%81%E5%85%AC%23&Refer=top"}, {"rank": "17", "name": "11月最后一天 ", "count": "555348", "link": "https://s.weibo.com//weibo?q=11%E6%9C%88%E6%9C%80%E5%90%8E%E4%B8%80%E5%A4%A9&Refer=top"}, {"rank": "18", "name": "2021金球奖 ", "count": "519958", "link": "https://s.weibo.com//weibo?q=2021%E9%87%91%E7%90%83%E5%A5%96&Refer=top"}, {"rank": "19", "name": "27岁脑瘫小伙考取高级网络工程师 ", "count": "517068", "link": "https://s.weibo.com//weibo?q=%2327%E5%B2%81%E8%84%91%E7%98%AB%E5%B0%8F%E4%BC%99%E8%80%83%E5%8F%96%E9%AB%98%E7%BA%A7%E7%BD%91%E7%BB%9C%E5%B7%A5%E7%A8%8B%E5%B8%88%23&Refer=top"}, {"rank": "20", "name": "广州一高校20多人发烧腹泻被隔离 ", "count": "511962", "link": "https://s.weibo.com//weibo?q=%23%E5%B9%BF%E5%B7%9E%E4%B8%80%E9%AB%98%E6%A0%A120%E5%A4%9A%E4%BA%BA%E5%8F%91%E7%83%A7%E8%85%B9%E6%B3%BB%E8%A2%AB%E9%9A%94%E7%A6%BB%23&Refer=top"}, {"rank": "21", "name": "王岳伦宣布已与李湘离婚后删博 ", "count": "508760", "link": "https://s.weibo.com//weibo?q=%23%E7%8E%8B%E5%B2%B3%E4%BC%A6%E5%AE%A3%E5%B8%83%E5%B7%B2%E4%B8%8E%E6%9D%8E%E6%B9%98%E7%A6%BB%E5%A9%9A%E5%90%8E%E5%88%A0%E5%8D%9A%23&Refer=top"}, {"rank": "22", "name": "女孩怀孕男友母亲灵魂三问 ", "count": "507612", "link": "https://s.weibo.com//weibo?q=%23%E5%A5%B3%E5%AD%A9%E6%80%80%E5%AD%95%E7%94%B7%E5%8F%8B%E6%AF%8D%E4%BA%B2%E7%81%B5%E9%AD%82%E4%B8%89%E9%97%AE%23&Refer=top"}, {"rank": "23", "name": "刺杀小说家获金鸡奖6项提名 ", "count": "505422", "link": "https://s.weibo.com//weibo?q=%23%E5%88%BA%E6%9D%80%E5%B0%8F%E8%AF%B4%E5%AE%B6%E8%8E%B7%E9%87%91%E9%B8%A1%E5%A5%966%E9%A1%B9%E6%8F%90%E5%90%8D%23&Refer=top"}, {"rank": "24", "name": "林郑月娥首次访问湖北 ", "count": "500905", "link": "https://s.weibo.com//weibo?q=%23%E6%9E%97%E9%83%91%E6%9C%88%E5%A8%A5%E9%A6%96%E6%AC%A1%E8%AE%BF%E9%97%AE%E6%B9%96%E5%8C%97%23&Refer=top"}, {"rank": "25", "name": "海市被封斛珠夫人 ", "count": "436179", "link": "https://s.weibo.com//weibo?q=%23%E6%B5%B7%E5%B8%82%E8%A2%AB%E5%B0%81%E6%96%9B%E7%8F%A0%E5%A4%AB%E4%BA%BA%23&Refer=top"}, {"rank": "26", "name": "科比宣布退役6周年 ", "count": "379279", "link": "https://s.weibo.com//weibo?q=%23%E7%A7%91%E6%AF%94%E5%AE%A3%E5%B8%83%E9%80%80%E5%BD%B96%E5%91%A8%E5%B9%B4%23&Refer=top"}, {"rank": "27", "name": "奥密克戎传染力比德尔塔增37.5% ", "count": "351747", "link": "https://s.weibo.com//weibo?q=%23%E5%A5%A5%E5%AF%86%E5%85%8B%E6%88%8E%E4%BC%A0%E6%9F%93%E5%8A%9B%E6%AF%94%E5%BE%B7%E5%B0%94%E5%A1%94%E5%A2%9E37.5%25%23&Refer=top"}, {"rank": "28", "name": "2021只剩最后一个月 ", "count": "342729", "link": "https://s.weibo.com//weibo?q=%232021%E5%8F%AA%E5%89%A9%E6%9C%80%E5%90%8E%E4%B8%80%E4%B8%AA%E6%9C%88%23&Refer=top"}, {"rank": "29", "name": "父亲得知女儿被亲时的反应 ", "count": "331527", "link": "https://s.weibo.com//weibo?q=%23%E7%88%B6%E4%BA%B2%E5%BE%97%E7%9F%A5%E5%A5%B3%E5%84%BF%E8%A2%AB%E4%BA%B2%E6%97%B6%E7%9A%84%E5%8F%8D%E5%BA%94%23&Refer=top"}, {"rank": "30", "name": "梁靖崑用亲吻国旗回击种族歧视 ", "count": "330488", "link": "https://s.weibo.com//weibo?q=%23%E6%A2%81%E9%9D%96%E5%B4%91%E7%94%A8%E4%BA%B2%E5%90%BB%E5%9B%BD%E6%97%97%E5%9B%9E%E5%87%BB%E7%A7%8D%E6%97%8F%E6%AD%A7%E8%A7%86%23&Refer=top"}, {"rank": "31", "name": "永远可以相信毛不易的嘴 ", "count": "324718", "link": "https://s.weibo.com//weibo?q=%23%E6%B0%B8%E8%BF%9C%E5%8F%AF%E4%BB%A5%E7%9B%B8%E4%BF%A1%E6%AF%9B%E4%B8%8D%E6%98%93%E7%9A%84%E5%98%B4%23&Refer=top"}, {"rank": "32", "name": "缇兰怀孕 ", "count": "321169", "link": "https://s.weibo.com//weibo?q=%23%E7%BC%87%E5%85%B0%E6%80%80%E5%AD%95%23&Refer=top"}, {"rank": "33", "name": "两车碰撞私家车主踹倒公交司机 ", "count": "317156", "link": "https://s.weibo.com//weibo?q=%23%E4%B8%A4%E8%BD%A6%E7%A2%B0%E6%92%9E%E7%A7%81%E5%AE%B6%E8%BD%A6%E4%B8%BB%E8%B8%B9%E5%80%92%E5%85%AC%E4%BA%A4%E5%8F%B8%E6%9C%BA%23&Refer=top"}, {"rank": "34", "name": "雪滴花剧本研读 ", "count": "302622", "link": "https://s.weibo.com//weibo?q=%23%E9%9B%AA%E6%BB%B4%E8%8A%B1%E5%89%A7%E6%9C%AC%E7%A0%94%E8%AF%BB%23&Refer=top"}, {"rank": "35", "name": "翟志刚实力抢镜王 ", "count": "301684", "link": "https://s.weibo.com//weibo?q=%23%E7%BF%9F%E5%BF%97%E5%88%9A%E5%AE%9E%E5%8A%9B%E6%8A%A2%E9%95%9C%E7%8E%8B%23&Refer=top"}, {"rank": "36", "name": "成都年轻人有多喜欢熬夜 ", "count": "280408", "link": "https://s.weibo.com//weibo?q=%23%E6%88%90%E9%83%BD%E5%B9%B4%E8%BD%BB%E4%BA%BA%E6%9C%89%E5%A4%9A%E5%96%9C%E6%AC%A2%E7%86%AC%E5%A4%9C%23&Refer=top"}, {"rank": "37", "name": "风起西州杀青 ", "count": "271871", "link": "https://s.weibo.com//weibo?q=%23%E9%A3%8E%E8%B5%B7%E8%A5%BF%E5%B7%9E%E6%9D%80%E9%9D%92%23&Refer=top"}, {"rank": "38", "name": "全球旅游业损失达2万亿美元 ", "count": "267506", "link": "https://s.weibo.com//weibo?q=%23%E5%85%A8%E7%90%83%E6%97%85%E6%B8%B8%E4%B8%9A%E6%8D%9F%E5%A4%B1%E8%BE%BE2%E4%B8%87%E4%BA%BF%E7%BE%8E%E5%85%83%23&Refer=top"}, {"rank": "39", "name": "我国正在研制针对变异株疫苗 ", "count": "257777", "link": "https://s.weibo.com//weibo?q=%23%E6%88%91%E5%9B%BD%E6%AD%A3%E5%9C%A8%E7%A0%94%E5%88%B6%E9%92%88%E5%AF%B9%E5%8F%98%E5%BC%82%E6%A0%AA%E7%96%AB%E8%8B%97%23&Refer=top"}, {"rank": "40", "name": "太空饮水机 ", "count": "256312", "link": "https://s.weibo.com//weibo?q=%E5%A4%AA%E7%A9%BA%E9%A5%AE%E6%B0%B4%E6%9C%BA&Refer=top"}, {"rank": "41", "name": "为什么冬天会更想找对象 ", "count": "253759", "link": "https://s.weibo.com//weibo?q=%23%E4%B8%BA%E4%BB%80%E4%B9%88%E5%86%AC%E5%A4%A9%E4%BC%9A%E6%9B%B4%E6%83%B3%E6%89%BE%E5%AF%B9%E8%B1%A1%23&Refer=top"}, {"rank": "42", "name": "70年前的今天中美空军血战大和岛 ", "count": "247296", "link": "https://s.weibo.com//weibo?q=%2370%E5%B9%B4%E5%89%8D%E7%9A%84%E4%BB%8A%E5%A4%A9%E4%B8%AD%E7%BE%8E%E7%A9%BA%E5%86%9B%E8%A1%80%E6%88%98%E5%A4%A7%E5%92%8C%E5%B2%9B%23&Refer=top"}, {"rank": "43", "name": "超10国确诊奥密克戎新冠变异株 ", "count": "241680", "link": "https://s.weibo.com//weibo?q=%23%E8%B6%8510%E5%9B%BD%E7%A1%AE%E8%AF%8A%E5%A5%A5%E5%AF%86%E5%85%8B%E6%88%8E%E6%96%B0%E5%86%A0%E5%8F%98%E5%BC%82%E6%A0%AA%23&Refer=top"}, {"rank": "44", "name": "交警副支队长遭前妻实名举报 ", "count": "216412", "link": "https://s.weibo.com//weibo?q=%23%E4%BA%A4%E8%AD%A6%E5%89%AF%E6%94%AF%E9%98%9F%E9%95%BF%E9%81%AD%E5%89%8D%E5%A6%BB%E5%AE%9E%E5%90%8D%E4%B8%BE%E6%8A%A5%23&Refer=top"}, {"rank": "45", "name": "我国现有核酸检测可检出奥密克戎 ", "count": "215139", "link": "https://s.weibo.com//weibo?q=%23%E6%88%91%E5%9B%BD%E7%8E%B0%E6%9C%89%E6%A0%B8%E9%85%B8%E6%A3%80%E6%B5%8B%E5%8F%AF%E6%A3%80%E5%87%BA%E5%A5%A5%E5%AF%86%E5%85%8B%E6%88%8E%23&Refer=top"}, {"rank": "46", "name": "和父母聊天能有多野 ", "count": "213538", "link": "https://s.weibo.com//weibo?q=%23%E5%92%8C%E7%88%B6%E6%AF%8D%E8%81%8A%E5%A4%A9%E8%83%BD%E6%9C%89%E5%A4%9A%E9%87%8E%23&Refer=top"}, {"rank": "47", "name": "现有疫苗对奥密克戎仍有效 ", "count": "208814", "link": "https://s.weibo.com//weibo?q=%23%E7%8E%B0%E6%9C%89%E7%96%AB%E8%8B%97%E5%AF%B9%E5%A5%A5%E5%AF%86%E5%85%8B%E6%88%8E%E4%BB%8D%E6%9C%89%E6%95%88%23&Refer=top"}, {"rank": "48", "name": "北极熊将驯鹿淹死后捕食 ", "count": "201713", "link": "https://s.weibo.com//weibo?q=%23%E5%8C%97%E6%9E%81%E7%86%8A%E5%B0%86%E9%A9%AF%E9%B9%BF%E6%B7%B9%E6%AD%BB%E5%90%8E%E6%8D%95%E9%A3%9F%23&Refer=top"}, {"rank": "49", "name": "奥密克戎 ", "count": "200501", "link": "https://s.weibo.com//weibo?q=%23%E5%A5%A5%E5%AF%86%E5%85%8B%E6%88%8E%23&Refer=top"}, {"rank": "50", "name": "上海58岁阿姨获世乒赛铜牌 ", "count": "188552", "link": "https://s.weibo.com//weibo?q=%23%E4%B8%8A%E6%B5%B758%E5%B2%81%E9%98%BF%E5%A7%A8%E8%8E%B7%E4%B8%96%E4%B9%92%E8%B5%9B%E9%93%9C%E7%89%8C%23&Refer=top"}], "name": "微博热搜"}, "weibo_topic": {"tops": [{"rank": "1", "name": "#什么样的爸爸算好爸爸#", "count": "5671讨论 2883.3万阅读", "link": "https://s.weibo.com/weibo?q=%23%E4%BB%80%E4%B9%88%E6%A0%B7%E7%9A%84%E7%88%B8%E7%88%B8%E7%AE%97%E5%A5%BD%E7%88%B8%E7%88%B8%23", "desc": "《朗读者》第三季节目中，讲述了野生动物保护者潘文石与女儿之间的父女情。在你看来，什么样的爸爸算好爸爸？来分享你的看法吧！"}, {"rank": "2", "name": "#你是讨好型人格吗#", "count": "5.8万讨论 2.5亿阅读", "link": "https://s.weibo.com/weibo?q=%23%E4%BD%A0%E6%98%AF%E8%AE%A8%E5%A5%BD%E5%9E%8B%E4%BA%BA%E6%A0%BC%E5%90%97%23", "desc": "电视剧《女心理师》全新单元人物小莫上线，跟着贺顿一起解读身边的讨好型人格，一同探索如何做更舒适的自己！"}, {"rank": "3", "name": "#遭遇上司打压该怎么办#", "count": "9046讨论 1183.6万阅读", "link": "https://s.weibo.com/weibo?q=%23%E9%81%AD%E9%81%87%E4%B8%8A%E5%8F%B8%E6%89%93%E5%8E%8B%E8%AF%A5%E6%80%8E%E4%B9%88%E5%8A%9E%23", "desc": "《住在我隔壁的甲方》打工人应该也时常遇到上司打压下属的情况，你会怎么办？"}, {"rank": "4", "name": "#女心理师对你的家庭教育有影响吗#", "count": "2万讨论 8526.6万阅读", "link": "https://s.weibo.com/weibo?q=%23%E5%A5%B3%E5%BF%83%E7%90%86%E5%B8%88%E5%AF%B9%E4%BD%A0%E7%9A%84%E5%AE%B6%E5%BA%AD%E6%95%99%E8%82%B2%E6%9C%89%E5%BD%B1%E5%93%8D%E5%90%97%23", "desc": "《 女心理师》首次聚焦心理问题，通过一个又一个来访者的故事，传递心理问题简单地纾解情绪的方法，并呼吁人们重视心理健康。这部剧对你的家庭教育有影响吗"}, {"rank": "5", "name": "#为什么冬天会更想找对象#", "count": "3471讨论 4815.6万阅读", "link": "https://s.weibo.com/weibo?q=%23%E4%B8%BA%E4%BB%80%E4%B9%88%E5%86%AC%E5%A4%A9%E4%BC%9A%E6%9B%B4%E6%83%B3%E6%89%BE%E5%AF%B9%E8%B1%A1%23", "desc": "《毛雪汪》里李雪琴表示自己在睡觉时被冻醒的时刻会渴望身边能有一个人的陪伴，毛不易和尚九熙也认为冬天太冷，大家宅在家里，且有很多温馨的节日，会让人们找对象的欲望更加强烈 ，你是怎么看待的呢？"}, {"rank": "6", "name": "#生育假会影响职场女性吗你怎么看#", "count": "2629讨论 4485.4万阅读", "link": "https://s.weibo.com/weibo?q=%23%E7%94%9F%E8%82%B2%E5%81%87%E4%BC%9A%E5%BD%B1%E5%93%8D%E8%81%8C%E5%9C%BA%E5%A5%B3%E6%80%A7%E5%90%97%E4%BD%A0%E6%80%8E%E4%B9%88%E7%9C%8B%23", "desc": "政策“请客”企业“买单”，不仅不能提高企业鼓励生育的积极性，而且还会造成企业在用工、招聘时有意回避育龄女性的现实。生育假会影响职场女性吗？你怎么看？"}, {"rank": "7", "name": "#和父母聊天能有多野#", "count": "5349讨论 2.3亿阅读", "link": "https://s.weibo.com/weibo?q=%23%E5%92%8C%E7%88%B6%E6%AF%8D%E8%81%8A%E5%A4%A9%E8%83%BD%E6%9C%89%E5%A4%9A%E9%87%8E%23", "desc": "和父母聊天是一种什么体验？我可能有一个假的爸爸妈妈！"}, {"rank": "8", "name": "#新冠变异毒株对全球经济有何影响#", "count": "672讨论 523.9万阅读", "link": "https://s.weibo.com/weibo?q=%23%E6%96%B0%E5%86%A0%E5%8F%98%E5%BC%82%E6%AF%92%E6%A0%AA%E5%AF%B9%E5%85%A8%E7%90%83%E7%BB%8F%E6%B5%8E%E6%9C%89%E4%BD%95%E5%BD%B1%E5%93%8D%23", "desc": "为何全球暴跌？市场害怕的是奥密克戎远超德尔塔毒株的传染性以及更强的免疫逃逸能力，后者意味着疫苗的防疫作用可能减弱。新冠变异毒株将对全球经济产生什么影响？"}, {"rank": "9", "name": "#2021印象深刻的男性角色#", "count": "2.7万讨论 4584.1万阅读", "link": "https://s.weibo.com/weibo?q=%232021%E5%8D%B0%E8%B1%A1%E6%B7%B1%E5%88%BB%E7%9A%84%E7%94%B7%E6%80%A7%E8%A7%92%E8%89%B2%23", "desc": "2021年已经接近尾声，盘点众多优秀的电视剧作品陪伴我们度过的时光，在众多的作品里，总有让你印象深刻的角色；bb，带上你们的“珍藏精美图、视频”一起来聊聊吧~"}, {"rank": "10", "name": "#如何减少对自己的精神内耗#", "count": "1.5万讨论 4086.2万阅读", "link": "https://s.weibo.com/weibo?q=%23%E5%A6%82%E4%BD%95%E5%87%8F%E5%B0%91%E5%AF%B9%E8%87%AA%E5%B7%B1%E7%9A%84%E7%B2%BE%E7%A5%9E%E5%86%85%E8%80%97%23", "desc": "精神内耗很严重的人是什么样子的？不爱社交，对生活失去热情，自卑敏感又压抑，厌恶自己，从内而外散发出“丧”的气息。那么有什么帮助解决精神内耗的tips呢？"}, {"rank": "11", "name": "#人类可能是宇宙中最高等的文明吗#", "count": "1572讨论 447.2万阅读", "link": "https://s.weibo.com/weibo?q=%23%E4%BA%BA%E7%B1%BB%E5%8F%AF%E8%83%BD%E6%98%AF%E5%AE%87%E5%AE%99%E4%B8%AD%E6%9C%80%E9%AB%98%E7%AD%89%E7%9A%84%E6%96%87%E6%98%8E%E5%90%97%23", "desc": "宇宙有多大？很大是吗？但是一定会有像地球的条件环境，刚好适应人类生存，供人类发展地方，这么神奇的地方宇宙中有没有呢？有的科学家说有，那只是理论上的结论，外星人，uFO还只是传说，有时人类应该更自信一些，至少到目前为止，地球人类文明在我们所知的宇宙中是最高级的，最高等的。"}, {"rank": "12", "name": "#新中国第一个喝可乐的男孩怎么样了#", "count": "1.2万讨论 3.1亿阅读", "link": "https://s.weibo.com/weibo?q=%23%E6%96%B0%E4%B8%AD%E5%9B%BD%E7%AC%AC%E4%B8%80%E4%B8%AA%E5%96%9D%E5%8F%AF%E4%B9%90%E7%9A%84%E7%94%B7%E5%AD%A9%E6%80%8E%E4%B9%88%E6%A0%B7%E4%BA%86%23", "desc": "从外资到国货，从物资缺乏到多样选择，新中国第一个喝可乐的小男孩现在怎样了？我们的生活又发生了哪些改变？"}, {"rank": "13", "name": "#如何评价金鸡奖入围名单#", "count": "2257讨论 1469.9万阅读", "link": "https://s.weibo.com/weibo?q=%23%E5%A6%82%E4%BD%95%E8%AF%84%E4%BB%B7%E9%87%91%E9%B8%A1%E5%A5%96%E5%85%A5%E5%9B%B4%E5%90%8D%E5%8D%95%23", "desc": "小码@电影全解码 带你用一张图解读第34届金鸡奖提名名单：最佳故事片、最佳导演、最佳男主角、最佳女主角、最佳中小成本故事片。"}, {"rank": "14", "name": "#如何看待好欢螺回应虫卵事件#", "count": "116讨论 325.7万阅读", "link": "https://s.weibo.com/weibo?q=%23%E5%A6%82%E4%BD%95%E7%9C%8B%E5%BE%85%E5%A5%BD%E6%AC%A2%E8%9E%BA%E5%9B%9E%E5%BA%94%E8%99%AB%E5%8D%B5%E4%BA%8B%E4%BB%B6%23", "desc": "针对近日有网络用户发文称在好欢螺螺蛳粉中吃出虫卵事件，好欢螺回应称，其调料包、菜包等均经过巴氏消毒灭菌处理，符合食品安全标准，商业诋毁时有发生，此次事件发酵迅速超乎常态，将对该事件进行核查。"}, {"rank": "15", "name": "#如何应对奥密克戎#", "count": "919讨论 893.6万阅读", "link": "https://s.weibo.com/weibo?q=%23%E5%A6%82%E4%BD%95%E5%BA%94%E5%AF%B9%E5%A5%A5%E5%AF%86%E5%85%8B%E6%88%8E%23", "desc": "近日，新冠病毒变异株“奥密克戎”受到关注，世卫组织将其全球总体风险评估为“非常高”。该如何应对？看↓"}, {"rank": "16", "name": "#留在大城市的原因是什么#", "count": "6619讨论 711.1万阅读", "link": "https://s.weibo.com/weibo?q=%23%E7%95%99%E5%9C%A8%E5%A4%A7%E5%9F%8E%E5%B8%82%E7%9A%84%E5%8E%9F%E5%9B%A0%E6%98%AF%E4%BB%80%E4%B9%88%23", "desc": "生活在大城市，大家总是觉得压力很大，也没有归属感。前几年还出现了逃离北上广的社会现象，但大城市里依然有很多年轻人在拼搏，你还留在大城市吗，你留在大城市的原因是什么，一起来聊聊吧。"}, {"rank": "17", "name": "#国际油价接下来怎么走#", "count": "1543讨论 243.7万阅读", "link": "https://s.weibo.com/weibo?q=%23%E5%9B%BD%E9%99%85%E6%B2%B9%E4%BB%B7%E6%8E%A5%E4%B8%8B%E6%9D%A5%E6%80%8E%E4%B9%88%E8%B5%B0%23", "desc": ""}, {"rank": "18", "name": "#熬夜之后如何恢复#", "count": "199讨论 122.1万阅读", "link": "https://s.weibo.com/weibo?q=%23%E7%86%AC%E5%A4%9C%E4%B9%8B%E5%90%8E%E5%A6%82%E4%BD%95%E6%81%A2%E5%A4%8D%23", "desc": "昨天晚上的你，熬夜了吗？很多人告诫自己一定要早睡，但一躺到床上就开始拿起手机刷社交网络、看剧、玩游戏。假如前一晚熬夜了，第二天如何恢复过来？"}, {"rank": "19", "name": "#当家主母的猫入驻微博#", "count": "1.5万讨论 2.3亿阅读", "link": "https://s.weibo.com/weibo?q=%23%E5%BD%93%E5%AE%B6%E4%B8%BB%E6%AF%8D%E7%9A%84%E7%8C%AB%E5%85%A5%E9%A9%BB%E5%BE%AE%E5%8D%9A%23", "desc": "当家主母的猫也开通了微博，并分享猫猫的日常遛弯视频。"}, {"rank": "20", "name": "#婚假怎样调整年轻人才能愉快结婚#", "count": "432讨论 122万阅读", "link": "https://s.weibo.com/weibo?q=%23%E5%A9%9A%E5%81%87%E6%80%8E%E6%A0%B7%E8%B0%83%E6%95%B4%E5%B9%B4%E8%BD%BB%E4%BA%BA%E6%89%8D%E8%83%BD%E6%84%89%E5%BF%AB%E7%BB%93%E5%A9%9A%23", "desc": "近日，“婚假太短，没时间结婚”的话题冲上热搜，引发网络热议。那么，婚假怎样调整，年轻人才能愉快结婚？"}, {"rank": "21", "name": "#女孩怀孕男友母亲灵魂三问#", "count": "3759讨论 2.1亿阅读", "link": "https://s.weibo.com/weibo?q=%23%E5%A5%B3%E5%AD%A9%E6%80%80%E5%AD%95%E7%94%B7%E5%8F%8B%E6%AF%8D%E4%BA%B2%E7%81%B5%E9%AD%82%E4%B8%89%E9%97%AE%23", "desc": "近日，河南郑州，董女士反映，10月份认识了男友赵某，11月份发现自己怀孕了，可谁知道对方回了一句：“咱俩以后不要见面了，孩子我也不要”后就消失再也联系不上。"}, {"rank": "22", "name": "#满洲里检出阳性样本60份#", "count": "4583讨论 1.3亿阅读", "link": "https://s.weibo.com/weibo?q=%23%E6%BB%A1%E6%B4%B2%E9%87%8C%E6%A3%80%E5%87%BA%E9%98%B3%E6%80%A7%E6%A0%B7%E6%9C%AC60%E4%BB%BD%23", "desc": "29日8时，内蒙古满洲里首轮全员核酸检测工作全面完成，共采集样本175554人份，检测出阳性样本60份。"}, {"rank": "23", "name": "#强制诱导学生有偿补课撤销教师资格#", "count": "1503讨论 6156.5万阅读", "link": "https://s.weibo.com/weibo?q=%23%E5%BC%BA%E5%88%B6%E8%AF%B1%E5%AF%BC%E5%AD%A6%E7%94%9F%E6%9C%89%E5%81%BF%E8%A1%A5%E8%AF%BE%E6%92%A4%E9%94%80%E6%95%99%E5%B8%88%E8%B5%84%E6%A0%BC%23", "desc": "《中华人民共和国教师法（修订草案）（征求意见稿）》发布。"}, {"rank": "24", "name": "#上海58岁阿姨获世乒赛铜牌#", "count": "5497讨论 2.2亿阅读", "link": "https://s.weibo.com/weibo?q=%23%E4%B8%8A%E6%B5%B758%E5%B2%81%E9%98%BF%E5%A7%A8%E8%8E%B7%E4%B8%96%E4%B9%92%E8%B5%9B%E9%93%9C%E7%89%8C%23", "desc": "北京时间11月29日凌晨，在世乒赛女子双打半决赛中，58岁的倪夏莲与搭档德纳特以0-3输给孙颖莎/王曼昱，锁定铜牌，这是倪夏莲时隔36年再次拿到世乒赛奖牌。"}, {"rank": "25", "name": "#教师法拟规定教师资格相应学历学位#", "count": "5389讨论 1.2亿阅读", "link": "https://s.weibo.com/weibo?q=%23%E6%95%99%E5%B8%88%E6%B3%95%E6%8B%9F%E8%A7%84%E5%AE%9A%E6%95%99%E5%B8%88%E8%B5%84%E6%A0%BC%E7%9B%B8%E5%BA%94%E5%AD%A6%E5%8E%86%E5%AD%A6%E4%BD%8D%23", "desc": "教师法拟规定教师资格相应学历学位，取得中小学教师资格应具备高等学校师范专业本科或其他相关专业本科毕业及其以上学历，并获得相应学位。更多↓"}, {"rank": "26", "name": "#吉野家使用发臭肉沫#", "count": "4376讨论 9749.1万阅读", "link": "https://s.weibo.com/weibo?q=%23%E5%90%89%E9%87%8E%E5%AE%B6%E4%BD%BF%E7%94%A8%E5%8F%91%E8%87%AD%E8%82%89%E6%B2%AB%23", "desc": "吉野家宣称给予顾客最新鲜、最高品质的食品，售卖“最好的牛肉饭”。而实际中，不仅新鲜难以保障，就连过期后的白菜、菠菜也会继续使用。制作麻婆豆腐的肉沫已经变臭发酸，油类没有检测标准，旧油添加新油继续使用，油质严重发黑，后厨卫生也令人担忧"}, {"rank": "27", "name": "#网曝连云港一公园老虎瘦骨嶙峋#", "count": "1178讨论 6245.1万阅读", "link": "https://s.weibo.com/weibo?q=%23%E7%BD%91%E6%9B%9D%E8%BF%9E%E4%BA%91%E6%B8%AF%E4%B8%80%E5%85%AC%E5%9B%AD%E8%80%81%E8%99%8E%E7%98%A6%E9%AA%A8%E5%B6%99%E5%B3%8B%23", "desc": "11月28日，江苏连云港，游客爆料称新浦公园内老虎骨瘦嶙峋，肚子凹陷严重，奄奄一息地躺在地上。29日，园方工作人员称，那只老虎最近肠胃不好，正在调理恢复中。"}, {"rank": "28", "name": "#学神宿舍3人直博清华1人保研东大#", "count": "521讨论 4239.2万阅读", "link": "https://s.weibo.com/weibo?q=%23%E5%AD%A6%E7%A5%9E%E5%AE%BF%E8%88%8D3%E4%BA%BA%E7%9B%B4%E5%8D%9A%E6%B8%85%E5%8D%8E1%E4%BA%BA%E4%BF%9D%E7%A0%94%E4%B8%9C%E5%A4%A7%23", "desc": "东南大学信息科学与工程学院040181班的106宿舍，四个人，张猛、杨清元、刘育铭、顾昊不仅在各方面取得了不菲的成绩，而且一同保研名校：3人直博清华、1人保研本校。"}, {"rank": "29", "name": "#瑞典辞职首相再次当选#", "count": "547讨论 6327.8万阅读", "link": "https://s.weibo.com/weibo?q=%23%E7%91%9E%E5%85%B8%E8%BE%9E%E8%81%8C%E9%A6%96%E7%9B%B8%E5%86%8D%E6%AC%A1%E5%BD%93%E9%80%89%23", "desc": "当地时间11月29日，瑞典电视台报道，瑞典议会再次进行投票，玛格达莱娜·安德松再次当选瑞典首相。"}, {"rank": "30", "name": "#怎样在职场中保持良好的心态#", "count": "6629讨论 1020.6万阅读", "link": "https://s.weibo.com/weibo?q=%23%E6%80%8E%E6%A0%B7%E5%9C%A8%E8%81%8C%E5%9C%BA%E4%B8%AD%E4%BF%9D%E6%8C%81%E8%89%AF%E5%A5%BD%E7%9A%84%E5%BF%83%E6%80%81%23", "desc": "电视剧《女心理师》正在优酷全网独播，看贺顿、钱开逸等人如何在工作中愈挫愈勇！"}, {"rank": "31", "name": "#成都年轻人有多喜欢熬夜#", "count": "1883讨论 7916.6万阅读", "link": "https://s.weibo.com/weibo?q=%23%E6%88%90%E9%83%BD%E5%B9%B4%E8%BD%BB%E4%BA%BA%E6%9C%89%E5%A4%9A%E5%96%9C%E6%AC%A2%E7%86%AC%E5%A4%9C%23", "desc": "一线城市和新一线城市的熬夜情况分别为73.77%、74.62%，其中广州凭借81.91%的经常熬夜人数占比夺得最爱熬夜一线城市TOP1，成都以63.77%的经常熬夜人数排名全国第八。"}, {"rank": "32", "name": "#你和父母多久没有合照了#", "count": "1万讨论 1.1亿阅读", "link": "https://s.weibo.com/weibo?q=%23%E4%BD%A0%E5%92%8C%E7%88%B6%E6%AF%8D%E5%A4%9A%E4%B9%85%E6%B2%A1%E6%9C%89%E5%90%88%E7%85%A7%E4%BA%86%23", "desc": "《朗读者》第三季中，康辉说自己曾经以为，与母亲合影的机会还有很多，然而母亲去世后，他翻遍手机相册，却发现母子二人的合照一张都没有。从胶卷相机到数码相机、智能手机，拍照的成本越来越低，但我们与家人的照片却越来越少了。你和父母多久没有合照了？"}, {"rank": "33", "name": "#手机边玩边充电会损害电池吗#", "count": "3362讨论 795.1万阅读", "link": "https://s.weibo.com/weibo?q=%23%E6%89%8B%E6%9C%BA%E8%BE%B9%E7%8E%A9%E8%BE%B9%E5%85%85%E7%94%B5%E4%BC%9A%E6%8D%9F%E5%AE%B3%E7%94%B5%E6%B1%A0%E5%90%97%23", "desc": "手机边玩边充电会损害电池吗？边玩边冲真的好么？除了发热量大以外，是不是也会对电池造成损耗呢？ ​"}, {"rank": "34", "name": "#专家称今年股市赚钱较难你认同吗#", "count": "274讨论 132.5万阅读", "link": "https://s.weibo.com/weibo?q=%23%E4%B8%93%E5%AE%B6%E7%A7%B0%E4%BB%8A%E5%B9%B4%E8%82%A1%E5%B8%82%E8%B5%9A%E9%92%B1%E8%BE%83%E9%9A%BE%E4%BD%A0%E8%AE%A4%E5%90%8C%E5%90%97%23", "desc": "经济学家、如是金融研究院院长@管清友 表示，A股今年明显是结构化走势，板块轮动特别快，所以今年赚钱是比较难的。"}, {"rank": "35", "name": "#暗恋会让自己觉得自卑吗#", "count": "3271讨论 1424.2万阅读", "link": "https://s.weibo.com/weibo?q=%23%E6%9A%97%E6%81%8B%E4%BC%9A%E8%AE%A9%E8%87%AA%E5%B7%B1%E8%A7%89%E5%BE%97%E8%87%AA%E5%8D%91%E5%90%97%23", "desc": "《导演请指教》当一个人暗恋另一个人的时候，ta往往会觉得自己很卑微，把自己放到一个极低的姿态——“见了他，她变得很低很低，低到尘埃里，从尘埃里开出花来”，在日复一日的思恋中忽视掉自我。\n\n倘若要重建自我，那就一定要从暗恋中抽身。"}, {"rank": "36", "name": "#为什么天冷就想吃火锅#", "count": "1651讨论 173万阅读", "link": "https://s.weibo.com/weibo?q=%23%E4%B8%BA%E4%BB%80%E4%B9%88%E5%A4%A9%E5%86%B7%E5%B0%B1%E6%83%B3%E5%90%83%E7%81%AB%E9%94%85%23", "desc": "火锅，作为花式多样、口味万千的美食种类，正在成为年轻人的聚餐首选。为什么一到冬天就想吃火锅？火锅又是如何成为一种新型社交方式的？"}, {"rank": "37", "name": "#人们为什么总是怀念过去#", "count": "1081讨论 101万阅读", "link": "https://s.weibo.com/weibo?q=%23%E4%BA%BA%E4%BB%AC%E4%B8%BA%E4%BB%80%E4%B9%88%E6%80%BB%E6%98%AF%E6%80%80%E5%BF%B5%E8%BF%87%E5%8E%BB%23", "desc": "过去无疑令人怀念，但我们毕竟是要向前看的，活在当下，开心的过好每一天"}, {"rank": "38", "name": "#父母不支持自己梦想怎么办#", "count": "1671讨论 533万阅读", "link": "https://s.weibo.com/weibo?q=%23%E7%88%B6%E6%AF%8D%E4%B8%8D%E6%94%AF%E6%8C%81%E8%87%AA%E5%B7%B1%E6%A2%A6%E6%83%B3%E6%80%8E%E4%B9%88%E5%8A%9E%23", "desc": "电视剧#陪你逐风飞翔# 中，争一妈妈因害怕争一受伤，不愿女儿追逐职业运动员的梦想，当父母不支持你的梦想时你会怎么办呢？带话题#父母不支持自己梦想怎么办# 参与讨论吧~"}, {"rank": "39", "name": "#如何看待App超范围采集个人信息#", "count": "2676讨论 957.7万阅读", "link": "https://s.weibo.com/weibo?q=%23%E5%A6%82%E4%BD%95%E7%9C%8B%E5%BE%85App%E8%B6%85%E8%8C%83%E5%9B%B4%E9%87%87%E9%9B%86%E4%B8%AA%E4%BA%BA%E4%BF%A1%E6%81%AF%23", "desc": "为何手机APP违法违规收集或窃取个人隐私行为屡禁不止、屡打不绝？"}, {"rank": "40", "name": "#中国将再向非方提供10亿剂疫苗#", "count": "2387讨论 1.1亿阅读", "link": "https://s.weibo.com/weibo?q=%23%E4%B8%AD%E5%9B%BD%E5%B0%86%E5%86%8D%E5%90%91%E9%9D%9E%E6%96%B9%E6%8F%90%E4%BE%9B10%E4%BA%BF%E5%89%82%E7%96%AB%E8%8B%97%23", "desc": "为实现非盟确定的2022年60%非洲人口接种新冠疫苗的目标，中国将再向非方提供10亿剂疫苗，其中6亿剂为无偿援助，4亿剂以中方企业与有关非洲国家联合生产等方式提供。"}, {"rank": "41", "name": "#男子为追回爱情报假警举报女友卖淫#", "count": "690讨论 3860.7万阅读", "link": "https://s.weibo.com/weibo?q=%23%E7%94%B7%E5%AD%90%E4%B8%BA%E8%BF%BD%E5%9B%9E%E7%88%B1%E6%83%85%E6%8A%A5%E5%81%87%E8%AD%A6%E4%B8%BE%E6%8A%A5%E5%A5%B3%E5%8F%8B%E5%8D%96%E6%B7%AB%23", "desc": "近日，@滁州公安在线 汊河派出所接男子王某电话报警称：其女友张某在汊河一小区内卖淫。接警后，民警迅速展开相关侦查工作，发现该报警人的描述不属实。经进一步询问，原来王某与女友发生争吵，女友出走后其多次寻找未果，试图通过报假警这种方式让警方找到其女友。"}, {"rank": "42", "name": "#微信群聊试行电商外链直接访问#", "count": "1162讨论 7668.7万阅读", "link": "https://s.weibo.com/weibo?q=%23%E5%BE%AE%E4%BF%A1%E7%BE%A4%E8%81%8A%E8%AF%95%E8%A1%8C%E7%94%B5%E5%95%86%E5%A4%96%E9%93%BE%E7%9B%B4%E6%8E%A5%E8%AE%BF%E9%97%AE%23", "desc": "据《声明》内容，该阶段调整主要为三点： 1、在点对点聊天场景中将可直接访问外部链接；2、在监管部门指导下，为贯彻安全底线原则，同时兼顾用户使用体验，将在群聊场景下试行开放电商类外部链接直接访问功能；3、后续计划开发自主选择模式，为用户提供外链管理功能。"}, {"rank": "43", "name": "#毕淑敏希望用干净手段抵达光明理想#", "count": "2539讨论 1887.5万阅读", "link": "https://s.weibo.com/weibo?q=%23%E6%AF%95%E6%B7%91%E6%95%8F%E5%B8%8C%E6%9C%9B%E7%94%A8%E5%B9%B2%E5%87%80%E6%89%8B%E6%AE%B5%E6%8A%B5%E8%BE%BE%E5%85%89%E6%98%8E%E7%90%86%E6%83%B3%23", "desc": "一个人活着，要使自己的幸福最大化，也要让别人因为你的存在，幸福感多一些。”2007年，当毕淑敏的小说《女心理师》出版时，她把这句话写在自序中。日前，接受中青报·中青网记者独家专访时，作家毕淑敏如是说：“我个人的价值观和方法论是，希望用干净的手段，抵达一个光明的理想。”"}, {"rank": "44", "name": "#上海试点研究生符合条件可直接落户#", "count": "2369讨论 6253.2万阅读", "link": "https://s.weibo.com/weibo?q=%23%E4%B8%8A%E6%B5%B7%E8%AF%95%E7%82%B9%E7%A0%94%E7%A9%B6%E7%94%9F%E7%AC%A6%E5%90%88%E6%9D%A1%E4%BB%B6%E5%8F%AF%E7%9B%B4%E6%8E%A5%E8%90%BD%E6%88%B7%23", "desc": "经上海市高校招生和就业工作联席会议研究，决定开放第二批2021年非上海生源应届普通高校毕业生进沪就业落户受理工作。"}, {"rank": "45", "name": "#中国从未邀请美国政客出席北京冬奥#", "count": "5672讨论 1.7亿阅读", "link": "https://s.weibo.com/weibo?q=%23%E4%B8%AD%E5%9B%BD%E4%BB%8E%E6%9C%AA%E9%82%80%E8%AF%B7%E7%BE%8E%E5%9B%BD%E6%94%BF%E5%AE%A2%E5%87%BA%E5%B8%AD%E5%8C%97%E4%BA%AC%E5%86%AC%E5%A5%A5%23", "desc": "知情人士 ：中国从未邀请美国政客来华出席北京冬奥会"}, {"rank": "46", "name": "#奥密克戎毒株或可逃避免疫保护#", "count": "597讨论 2923.6万阅读", "link": "https://s.weibo.com/weibo?q=%23%E5%A5%A5%E5%AF%86%E5%85%8B%E6%88%8E%E6%AF%92%E6%A0%AA%E6%88%96%E5%8F%AF%E9%80%83%E9%81%BF%E5%85%8D%E7%96%AB%E4%BF%9D%E6%8A%A4%23", "desc": "当地时间28日，美国国家过敏和传染病研究所所长福奇在接受美国媒体采访时表示，“奥密克戎”很容易传播，可能逃避民众从新冠疫苗或先前感染中获得的免疫力。"}, {"rank": "47", "name": "#团伙雇佣大学生1个月洗钱9000万#", "count": "2888讨论 5319.3万阅读", "link": "https://s.weibo.com/weibo?q=%23%E5%9B%A2%E4%BC%99%E9%9B%87%E4%BD%A3%E5%A4%A7%E5%AD%A6%E7%94%9F1%E4%B8%AA%E6%9C%88%E6%B4%97%E9%92%B19000%E4%B8%87%23", "desc": "近日，江苏海门公安成功捣毁一个“跑分”犯罪团伙，抓获的10名嫌疑人中6人为在校大学生。"}, {"rank": "48", "name": "#光大证券前董事长薛峰被调查#", "count": "439讨论 1586.6万阅读", "link": "https://s.weibo.com/weibo?q=%23%E5%85%89%E5%A4%A7%E8%AF%81%E5%88%B8%E5%89%8D%E8%91%A3%E4%BA%8B%E9%95%BF%E8%96%9B%E5%B3%B0%E8%A2%AB%E8%B0%83%E6%9F%A5%23", "desc": "第一财经记者从权威人士处了解到，光大证券前董事长薛峰，已于数月前被有关方面带走调查，核心事由可能涉及此前沸沸扬扬的明星跨国并购案——暴风集团收购英国体育版权公司MPS事件。"}, {"rank": "49", "name": "#67岁住院病人砍伤医护和病人后跳楼身亡#", "count": "829讨论 7163.7万阅读", "link": "https://s.weibo.com/weibo?q=%2367%E5%B2%81%E4%BD%8F%E9%99%A2%E7%97%85%E4%BA%BA%E7%A0%8D%E4%BC%A4%E5%8C%BB%E6%8A%A4%E5%92%8C%E7%97%85%E4%BA%BA%E5%90%8E%E8%B7%B3%E6%A5%BC%E8%BA%AB%E4%BA%A1%23", "desc": "住院病人熊某明（男，67岁）将一名医护人员和一名住院病人砍伤后跳楼身亡。"}, {"rank": "50", "name": "#病毒出现新变异防疫好办法要坚持#", "count": "4138讨论 7912.2万阅读", "link": "https://s.weibo.com/weibo?q=%23%E7%97%85%E6%AF%92%E5%87%BA%E7%8E%B0%E6%96%B0%E5%8F%98%E5%BC%82%E9%98%B2%E7%96%AB%E5%A5%BD%E5%8A%9E%E6%B3%95%E8%A6%81%E5%9D%9A%E6%8C%81%23", "desc": "有效的防疫“好办法”，戴口罩、勤洗手、多通风等，都需要大家不折不扣地继续坚持，千万别大意！"}], "name": "微博话题"}, "zhihu": {"tops": [{"rank": 1, "name": "梅西夺得个人第 7 座金球奖，如何评价他在 2021 年的表现？", "count": "723 万热度", "link": "https:\\\\www.zhihu.com\\question\\502567942", "desc": "梅西获得个人生涯第七座金球奖！这是梅西第 7 次获得金球奖奖杯，再次拉大了与其他人的差距。 20-21 赛季，梅西代表巴萨出战 48 场比赛，打进 38 球，送出 18 次助攻，帮助球队赢得了上赛季的国王杯冠军。 本赛季，梅西转会巴黎，截至目前代表球队出战 11 场比赛，打进 4 球，送出 4 次助攻。 今年，梅西获得了个人国家队的首座大赛奖杯，帮助阿根廷队赢得美洲杯冠军，整届比赛中他打进 4 个进球，送出 5 次助攻。 梅西 7 度夺得金球奖，他发表了自己的获奖感言。 梅西：“今天我在巴黎。我非常高兴，真的非常高兴，我真的很想继续努力，达到新的目标。我不知道还有多少年，但我真的很享受自己的生涯。我感谢我在巴萨，巴黎和阿根廷的队友，还有所有的教练。 「我想提到罗伯特 - 莱万多夫斯基，与你竞争真的是一种荣幸。每个人都知道，你是去年的最大赢家。我认为法国足球应该授予你 2020 年金球奖，这是你应得的，你应该拥有它」"}, {"rank": 2, "name": "如何看待《2021 中国城市租住生活蓝皮书》称 10 年内超 2 亿国人要租房？", "count": "701 万热度", "link": "https:\\\\www.zhihu.com\\question\\501343229", "desc": "《2021 中国城市租住生活蓝皮书》推出，报告指出租房需求越来越大，尤其是长租需求一直增长。租户对住房质量的要求也进一步提高…关于这份蓝皮书，大家有什么看法吗？面对目前的租赁市场，我们该怎么去合理的去租房？或者租房产业还有什么机遇或者趋势吗？"}, {"rank": 3, "name": "如何看待野猪糟蹋庄稼，夫妻猎杀 8 头被判缓刑？怎样更好地治理「野猪灾」？", "count": "328 万热度", "link": "https:\\\\www.zhihu.com\\question\\502124163", "desc": "近日，河南省南阳市淅川县一对夫妇在 3 个月内猎杀了至少 8 头野猪，法院以非法狩猎罪分别判处两人：有期徒刑 1 年 6 个月，缓刑 2 年；有期徒刑 1 年，缓刑 2 年。 庭审中，被告人吴某辩称：「野猪给地里庄稼糟蹋得非常严重，才灭了它。麦子损失了 30 多亩，吃得也没啥了，100 多亩玉米也被吃得 70 多亩绝收。现在认识到了自己的错误，愿意认罪认罚。」 近年来，我国一些地方的野猪种群数量不断扩大，甚至出现了泛滥成灾的局面。在江苏南京，近日发生了多起由野猪肇事引发的交通事故；四川通江县的村民也因境内野猪随意啃食、践踏庄稼而头疼不已；11 月 17 日，安徽宣城的一位市民在途经省道时拍到几十只野猪排队过马路的场景。野猪泛滥，拿它们怎么办？野猪糟蹋庄稼，「100 多亩玉米被吃得 70 多亩绝收」，夫妻猎杀 8 头被判缓刑！多地暴发「野猪灾」，拿它们没办法了？"}, {"rank": 4, "name": "如何看待重庆一窃贼被抓时正学习罗翔的刑法学讲义？犯罪分子学习刑法知识出于什么心理?", "count": "223 万热度", "link": "https:\\\\www.zhihu.com\\question\\502161756", "desc": "近日，重庆渝中区大阳沟派出所侦破了一起以教人刷单为名，实施盗窃手机的系列案件，在抓捕现场，民警意外发现犯罪嫌疑人居然在学习罗翔所著的《刑法学讲义》、画重点。民警忍不住问：“你 15 日那天，拿人家的手机，属于抢夺呢？诈骗呢？还是盗窃呢？嫌疑回答属于「侵占他人财产」，民警告知实际上这属于盗窃。警方提醒，学法知法虽有必要，但守法才是问题的核心。真「刑」！嫌犯被抓时正学习罗翔的刑法学讲义"}, {"rank": 5, "name": "工作原因每天 2 小时极限通勤，怎么让自己好受点？", "count": "140 万热度", "link": "https:\\\\www.zhihu.com\\question\\502404272", "desc": "现在的工作党每天都处在极度饱和，时间被压缩的状态，尤其是早晚通勤，遇到长时间堵车更是无法避免焦虑的情绪。 反正我基本上每天通勤都处于极限 2 小时的状态，在车上的时间较多，所以也比较看重车上的一些智能功能啊，交互系统什么的，这些要是很实用的话，能够转移注意力，有事可做，是真的可以让通勤路上好受不少的。另外也想知道大家还有哪些路上减压解乏的技巧？ 同时也想和各位车主还有汽车爱好者们探讨一下关于现在车机系统的发展现状，未来有没有可能出现更新颖的功能，为饱受长时间通勤，路上堵车困扰的打工人们提供一些方便？"}, {"rank": 6, "name": "一个人的旅行可以有多爽？", "count": "106 万热度", "link": "https:\\\\www.zhihu.com\\question\\500462027", "desc": "\"},\"imageArea\":{\"url\":\"https:\\u002F\\u002Fpic4.zhimg.com\\u002F50\\u002Fv2-9ad16eaa7f65f9a842253e5be3e77739_b.jpg"}, {"rank": 7, "name": "日本宣布禁止所有外国旅客入境，如何看待奥密克戎新冠变种对各国影响？", "count": "103 万热度", "link": "https:\\\\www.zhihu.com\\question\\502392008", "desc": "据界面新闻，日本放送协会（NHK）11 月 29 日报道，日本首相岸田文雄宣布，日本将禁止所有外国旅客入境，11 月 30 日起生效。 日本此前允许海外商务访问者和学生入境。近期，由于担心奥密克戎新冠变种而禁止来自南非和其他非洲国家的人入境。 29 日上午，日媒报道称，日本政府将宣布重新暂停允许商务访客和留学生入境，这意味着日本将实际上禁止所有外国旅客入境。 日本此前允许海外商务访问者和学生入境。近期，由于担心奥密克戎新冠变种而禁止来自南非和其他非洲国家的人入境。 共同社报道称，日本首相岸田文雄将在当地时间下午 1 点 10 分公布边境措施。"}, {"rank": 8, "name": "武松在景阳冈喝了 18 碗酒，外加两斤熟牛肉，正常人的胃一次性能塞这么多东西下去吗？", "count": "95 万热度", "link": "https:\\\\www.zhihu.com\\question\\36171900", "desc": "关于武松的饭量"}, {"rank": 9, "name": "考研前二十几天该放弃吗?", "count": "94 万热度", "link": "https:\\\\www.zhihu.com\\question\\502063029", "desc": "考研前二十几天，完全没准备好，想放弃二战了，但身边人都在说坚持，可每天都学不进去，该如何"}, {"rank": 10, "name": "当孩子问「为什么讨好别人叫做“拍马屁”而不是“拍牛屁”“拍羊屁”」如何回答？", "count": "82 万热度", "link": "https:\\\\www.zhihu.com\\question\\501515073", "desc": "\"},\"imageArea\":{\"url\":\"https:\\u002F\\u002Fpic2.zhimg.com\\u002F80\\u002Fv2-9303fccd490978abcd1f25a58ce750e3_1440w.jpg?source=1940ef5c"}, {"rank": 11, "name": "西南交大通报男生进女卫生间偷拍事件，称「勒令该生退学，交由警方调查处理」，如何看待这一结果？", "count": "75 万热度", "link": "https:\\\\www.zhihu.com\\question\\502418129", "desc": "西南交通大学 11 月 29 日通过其官方微博发布《情况通报》：2021 年 11 月 20 日上午 11 时，该校一名男生进入教学楼女卫生间偷拍。涉事男生已交由警方调查处理。经学校研究决定，勒令该生退学。"}, {"rank": 12, "name": "如果孩子问「爸爸和妈妈为什么要生下我」该如何回答？", "count": "69 万热度", "link": "https:\\\\www.zhihu.com\\question\\446727436", "desc": "\"},\"imageArea\":{\"url\":\"https:\\u002F\\u002Fpic4.zhimg.com\\u002F50\\u002Fv2-ea52c17c06934098094c534c83cca653_b.jpg"}, {"rank": 13, "name": "清华保安是如何快速分辨是否是本校学生？", "count": "59 万热度", "link": "https:\\\\www.zhihu.com\\question\\23165130", "desc": "RT，西门的保安，那是火眼金睛啊，隔壁的同学都被拦了好多次。"}, {"rank": 14, "name": "媒体评多地延长生育假，「相关政策应到位，生育假成本全由企业负担不现实」，如何确保生育假政策落实到位？", "count": "57 万热度", "link": "https:\\\\www.zhihu.com\\question\\502367239", "desc": "不得不说，各地纷纷增加生育假，这是对国家三孩生育政策的积极呼应与具体化，对此当持开放态度。但要真正落实这些措施，有一些细节还需厘清。 首先，生育假带来的成本问题必须正视，这部分成本全由企业负担显然是不现实的。政策「请客」企业「买单」，不仅不能提高企业鼓励生育的积极性，而且还会造成企业在用工、招聘时有意回避育龄女性的现实。而这也是带薪休假推行多年成效不大的原因。只有政府财政切实分担起一部分生育成本，在减免税费外，补偿企业的雇佣成本，企业才能有意愿配合这项政策的落地。 其次，生育假对职场女性的影响也应正视。浙江新政中明确提出，休生育假不影响晋级、调整工资、计算工龄。但生育者在休假期间的活由谁来干，休完假之后其岗位还在不在，这都是问题。 「三孩」来了，不断走低的人口出生率似乎在告诉我们一个道理——构建生育友好型社会，必须有平衡各方利益的方案，也只有这样的方案才能行得通、通得久。 生育假只是提升生育率、构建生育友好型社会的一部分。从大处讲，调整现有住房结构、完善普惠性托育、消除教育焦虑，从小处看，对哺乳期母亲上下班时间的设定更加弹性，在单位等各种场所增加更加人性化的哺乳室等，都需要政府部门从以人为本的角度去加以考虑。 来源：光明日报"}, {"rank": 15, "name": "如何看待国际乒联针对「世乒赛中国选手遭辱骂」发表声明，称反对一切形式的种族主义？", "count": "54 万热度", "link": "https:\\\\www.zhihu.com\\question\\502320807", "desc": "据北晚在线，北京时间 11 月 27 日上午，在美国休斯敦的世界乒乓球锦标赛（下称世乒赛）的男单八分之一决赛期间，看台上突然有观众对中国运动员梁靖崑大喊「黄香蕉」、「黄香蕉」。 这场比赛上，梁靖崑的对手是来自英国的皮切福德。比赛开打以来，比赛双方就展开了激烈的交锋，在比分上你追我赶，经过一轮短暂的比分落后，梁靖崑逆势反超，把总分拉到了 3:3。 当争夺决胜局比分到 8:4 时，刚刚赢下一球的皮切福德向裁判示意要求休息，吃起了别人递过来的一根香蕉补充体力。 表面看，这股起哄声是在说皮切福德吃香蕉，但在英语俚语中，「香蕉」也因其颜色有侮辱黄种人的含义。结合这名男子起哄的现场情况看，他实际的意思很可能是针对梁靖崑进行种族主义的侮辱。 在这名男子起哄时，梁靖崑正在和教练交流，并没有应声回头，或许因为赛况紧张且刚刚丢掉一球，梁靖崑的神情较为凝重，似乎正专注思考比赛战术，没有受到起哄的影响。大概是有工作人员注意并制止了这个情况，在起哄声响起不久后，这名男子的声音就没有再出现了。 皮切福德本人暂时尚未对自己在吃香蕉时遇到有人起哄一事做出回应。但从过往资料看，比赛时吃香蕉似乎是皮切福德的一个习惯。在 2016 年的世乒赛上，皮切福德在对阵波兰运动员时也曾在休息时吃了一根香蕉，还被摄影师拍下了这一幕。 28 日晚，@ITTF 国际乒联发表声明称，国际乒乓球联合会强烈反对一切形式的种族主义。 乒乓球大家庭是一个由 227 个会员协会组成的全球社区群体，多样性让我们团结在一起。 「我们绝不容忍任何种族主义言论或行为，我们正与当地组委会紧密合作，以杜绝我们的比赛中再次发生种族主义事件。」"}, {"rank": 16, "name": "黑龙江一女公务员狂扇母亲耳光，单位称其已被警方拘留，纪检部门也已立案 ，可能会有怎样的处理结果？", "count": "50 万热度", "link": "https:\\\\www.zhihu.com\\question\\502390260", "desc": "11 月 26 日，黑龙江佳木斯，一则女子殴打年迈母亲的视频在网上热传。视频显示，女子不断推搡母亲，狂扇母亲耳光并称：「把字给我签上！」其间，有人前来劝阻，但女子仍然继续施暴。29 日，佳木斯市自然资源和规划局称，打人女子系该单位公务员，纪检监察机关已对其立案审查，并表示警方已对打人女子作出拘留 15 日并处罚金 1000 元的决定，打人原因警方正在调查，单位也会发布通报给大家一个交代。 来源：时间视频黑龙江一女公务员狂扇母亲耳光：把字给我签上！单位称纪检部门已立案 _ 女子 _ 佳木斯 _ 打人"}, {"rank": 17, "name": "如何看待媒体曝出李铁与经纪公司保持密切关系，参与球员运作与牟利？", "count": "47 万热度", "link": "https:\\\\www.zhihu.com\\question\\502344102", "desc": "李铁下课，了犹未了 《足球报》今日对李铁与武汉队以及经纪公司之间的关系再度进行了曝光。据报道，李铁与一家名叫「科曼得体育」的经纪公司关系密切，且这早已是公开的秘密。 据此前报道，中国足协已经传出消息，国管部已经将李铁执教以来的所有情况整理成报告，上报总局。新任国足主帅也已有了候补人选，只待官宣后就将进入下一个主帅周期。据悉，足协对李铁执教的成绩基本满意，但主要问题在于场外因素。 除了此前在社媒中「打广告」、以及与武汉队不清不楚的关系之外，《足球报》表示，李铁还通过经纪公司，深入插手了多名球员的转会事宜。 据报道，李铁与一家名为「科曼得体育」的经纪公司保持密切关系，这在业内是公开的秘密，即便目前李铁已经与武汉俱乐部无关，但武汉队几乎所有的球员签约转会都是经这家公司之手。该公司的介绍中多次提及李铁：「与清水鼓动、李铁 8 号公园签订三方合作协议、教练员培训班项目」、「长期向沈阳李铁 8 号公园足球俱乐部派遣日本教练员 2 名」、「现中国国家队主教练李铁，为科曼得体育首席顾问，有深度合作」。 据报道，登录企查查，可以查到与李铁关联企业共有 8 家，但其中并不包括这家经纪公司，可见国足主帅「深度合作」经纪公司业务确实没办法放在明处。该公司 2020 年发给球员家长的公司介绍文案中，其展示的部分签约球员中，包括刘云、明天、郭田雨、徐新和段刘愚等，但据《足球报》表示，这里的球员有一些并非是他们公司旗下的球员，只是他们一直想签约的球员。 《足球报》透露，围绕这家公司和李铁，从 2020 年初开始就有传闻，其中包括：有短暂入选李铁国家队的球员，被要求签约这家经纪公司，拒绝签约的球员接下来没能再入选国足，惹得这位国脚所在队的新闻官到处跟记者们抱怨；有国脚转会中超豪门，该经纪公司以李铁帮忙牵线为由向球员要钱，被拒绝后，此国脚也在国足消失；有些球员入选国足后一直被该公司争取签约，但争取不到的就无法取得出场机会，随后就被放弃… 《足球报》最后总结到，若这些传闻属实，那么李铁就确实存在利用国脚资格牟利的情况；即使传闻不属实，那么李铁也不应该让经纪公司打着自己的旗号牟利。这些传闻对于李铁的未来发展有可能造成障碍，他需要直面这些问题，给出正面回应，还自己一个清白。"}, {"rank": 18, "name": "如何看待联发科高管称「全球只有一家公司有芯片发热问题，且不是我们」？这家公司是谁？为何出现发热情况？", "count": "46 万热度", "link": "https:\\\\www.zhihu.com\\question\\501740288", "desc": "近日，联发科公司的副总裁兼营销总经理 Finbarr Moynihan 在接受 AndroidAuthority 采访时表示对该处理器有信心，他称：「我认为大家都明白，它并没有提供承诺或预期的体验，对吗？我想我要说的是，我们非常有信心，而且显然我们正在向我们的主要客户提供这款芯片的样品，我们得到的反馈也是相当正向的。” Moynihan 还称：「当涉及到设备与设备之间的比较时，相信明年的旗舰产品我们在功耗方面会有优势。当然，我们预计所有的主流厂商在 2022 年转向 4 纳米设计（无论是台积电还是三星），这应该会带来更好的电源效率。」 「现在只有一家公司在发热方面有问题。而且不是我们。」联发科的全球公关总监 Kevin Keating 补充道，「竞争对手喜欢在联发科身上做文章，但我们没有发热问题。」 联发科：全球只有一家公司有芯片发热问题，且不是我们 - IT 之家"}, {"rank": 19, "name": "国内女性武打演员是出现断层了吗？", "count": "43 万热度", "link": "https:\\\\www.zhihu.com\\question\\501965465", "desc": "在达人秀上看到了一个挺可爱的武打演员，叫梁壁荧，听她说想拍动作戏，脑海中盘算了下，好像这几年确实没啥新的女性武打演员出来了。"}, {"rank": 20, "name": "几百和几千的羽绒服，到底差在哪里？", "count": "39 万热度", "link": "https:\\\\www.zhihu.com\\question\\500411245", "desc": "\"},\"imageArea\":{\"url\":\"https:\\u002F\\u002Fpic1.zhimg.com\\u002F50\\u002Fv2-80321c1674cd724da773f6f64c43a52c_720w.jpg?source=1940ef5c"}, {"rank": 21, "name": "自 2013 年中国初婚人数连续 7 年下降近半，创近 17 年新低，年轻人为何不愿意结婚了？", "count": "34 万热度", "link": "https:\\\\www.zhihu.com\\question\\501778105", "desc": "《中国统计年鉴 2021》显示，2020 年，结婚登记人数共计 814.33 万对，较 2019 年减少了 113 万对。这也是自 2013 年达到 1346.93 万对后，连续 7 年下降；这也创下自 2003 年（811.4 万对）以来近 17 年的新低。相比 2013 年的最高峰，2020 年结婚人数下降了 39.5%，接近四成。 结婚登记数据包括初婚人数和再婚人数，相比再婚人数，初婚人数与出生人口的关系更为密切。2013 年也是初婚人数的最高峰，达到 2385.96 万人。而到 2020 年，初婚人数为 1228.6 万人，7 年下降 48.5%，接近一半。比结婚对数降幅多了 9 个百分点。（第一财经）"}, {"rank": 22, "name": "卢伟冰称 Redmi K50 系列「不能用焊门员来形容，太强了」，到底有多强？你有哪些期待？", "count": "29 万热度", "link": "https:\\\\www.zhihu.com\\question\\502284084", "desc": "小米集团合伙人、中国区、国际部总裁、 Redmi 品牌总经理卢伟冰近日在社交媒体与网友互动时表示，Redmi K50 系列「已不能用焊门员来形容，太强了」。 此前，卢伟冰 11 月 1 日曾透露，今年没有 Redmi K40S，后面将准备 Redmi 新一代旗舰 K50。卢伟冰剧透 Redmi K50 系列：不能用焊门员来形容，太强了"}, {"rank": 23, "name": "谷歌翻译系统出现恶毒攻击中国词汇，谷歌是否该承担责任？对此事你怎么看？", "count": "28 万热度", "link": "https:\\\\www.zhihu.com\\question\\501898228", "desc": "【环球网报道】正常人为什么要在英文翻译里输中文？ 今天微博上有多位网友发现了一个令人非常气愤的情况，令＃谷歌翻译#成为引发很多人反感的标签。原因是网友发现，在谷歌翻译的英文翻中文程序中，在英文对话框输入「艾滋病毒」等相关词汇，对应的中文翻译就会出现恶毒攻击中国的词汇。 环球网记者测试后进一步发现，在英翻中的英文对话框输入「新闻」「传播」等词汇，中文部分显示的仍然是「新闻」「传播」。但在英文对话框输入「艾滋病毒」等类似词汇，中文翻译就会显示恶毒攻击中国的词汇。谷歌翻译系统出现恶毒攻击中国词汇，网友怒斥「真恶心！」谷歌回应"}, {"rank": 24, "name": "《当家主母》剧组称在拍摄中小猫并未死亡，目前仍健在，剧组已经报案，事件后续或将如何发展？", "count": "9 万热度", "link": "https:\\\\www.zhihu.com\\question\\502354428", "desc": "近日，在《当家主母》剧组采访猫主人说猫还安好，只是外出玩耍后，当家主母群演称猫被电死，再次引发争议。29 日凌晨，电视剧当家主母再发声明回应，称该言论与事实严重相悖，在拍摄中小猫并未死亡，也没有受伤，目前依然平安健在，剧组已经报案，将追究造谣者的刑事责任。 ​ 《当家主母》凌晨发布声明：我们报案了！ | 每经网"}, {"rank": 25, "name": "如果把动画《英雄联盟双城之战》中的希尔科做成英雄，会有什么技能？", "count": "6 万热度", "link": "https:\\\\www.zhihu.com\\question\\501900696", "desc": "\"},\"imageArea\":{\"url\":\"https:\\u002F\\u002Fpic2.zhimg.com\\u002F50\\u002Fv2-4cf875c0310b39ff7f64170052e60e08_b.jpg"}, {"rank": 26, "name": "一个玩网抑云的 CSGO 玩家会说怎么样的话？", "count": "6 万热度", "link": "https:\\\\www.zhihu.com\\question\\413300124", "desc": "\"},\"imageArea\":{\"url\":\"https:\\u002F\\u002Fpic4.zhimg.com\\u002F80\\u002Fv2-bb8270f22d1b7913d5685a279733117f_720w.jpg?source=1940ef5c"}, {"rank": 27, "name": "如何看待荣耀 60 系列手机的外观设计，你会喜欢吗？", "count": "6 万热度", "link": "https:\\\\www.zhihu.com\\question\\501704952", "desc": "近日，荣耀 60 系列的外观设计提前曝光。新机升级为全新的四曲面屏，相对于之前的四曲屏在工艺上有较大升级，实现了平面屏幕与曲面盖板的完美贴合；背部采用了双圆与双戒环设计，并利用钻彩工艺，打磨效果，独创银河系里漫天星光的配色。对于 12 月 1 日即将发布的荣耀 60 系列的手机外观设计，你会喜欢吗？"}, {"rank": 28, "name": "如何看待 2021 年轻人熬夜报告，互联网行业人员熬夜不是最狠的？你都是因为什么熬夜？", "count": "6 万热度", "link": "https:\\\\www.zhihu.com\\question\\502345227", "desc": "几点睡才算熬夜？哪个城市的年轻人最爱熬夜？年轻人熬夜都喜欢干什么？关于熬夜，年轻人似乎有说不完的话题，对于大多数年轻一代而言，夜晚有着特殊的魔力。为此，36 氪旗下后浪研究所发起了一项关于年轻人「熬夜」调查。 结果显示，4 成的年轻人几乎每天都熬夜，而 6 成以上的年轻人理想状态依然是「早睡早起」[月亮]；熬夜最狠的并不是互联网行业，自由职业者似乎在深夜会思考更多；越是单身的人睡的越晚，00 后虽然更年轻，但却没有 95 后能熬…"}, {"rank": 29, "name": "如何评价华晨宇回应职业黑粉的新歌《黑白艺术家》？", "count": "6 万热度", "link": "https:\\\\www.zhihu.com\\question\\502282790", "desc": "\"},\"imageArea\":{\"url\":\"https:\\u002F\\u002Fpic3.zhimg.com\\u002F80\\u002Fv2-23b4c729927368ee473d72031e2827c7_720w.png"}, {"rank": 30, "name": "请光学的研究生或者博士生回答我，在学校光学实验室做光学实验会不会伤害眼睛？", "count": "6 万热度", "link": "https:\\\\www.zhihu.com\\question\\488382559", "desc": "会不会对眼睛造成不可逆伤害？光学实验里是否有有毒物质？对女性或者孕妇造成伤害的？"}, {"rank": 31, "name": "你心目中的宋词十首巅峰之作是哪几篇？", "count": "6 万热度", "link": "https:\\\\www.zhihu.com\\question\\495059487", "desc": "\"},\"imageArea\":{\"url\":\"https:\\u002F\\u002Fpica.zhimg.com\\u002Fv2-6573949de9191399fa500abd7f20048f_720w.jpg?source=2044ae36"}, {"rank": 32, "name": "有哪些汽车知识，是一个成年人应该知道的？", "count": "6 万热度", "link": "https:\\\\www.zhihu.com\\question\\501593524", "desc": "\"},\"imageArea\":{\"url\":\"https:\\u002F\\u002Fpic3.zhimg.com\\u002F50\\u002Fv2-e0428b2da70bec1fa295b3f224e1a0b7_b.jpg"}, {"rank": 33, "name": "华为能设计出 M1 这样的芯片吗？", "count": "6 万热度", "link": "https:\\\\www.zhihu.com\\question\\495698750", "desc": "\"},\"imageArea\":{\"url\":\"https:\\u002F\\u002Fpic3.zhimg.com\\u002F50\\u002Fv2-79fc20a6be90e546c58283a9fd0ea22c_b.jpg"}, {"rank": 34, "name": "假如你进入了 a 岛动物园规则怪谈中的那个动物园，你会做什么呢？", "count": "6 万热度", "link": "https:\\\\www.zhihu.com\\question\\502398786", "desc": "是保证自己能安全出去，还是想尽一切办法在动物园活下来，亦或者是与「它」一较高下？ 动物园规则如下："}, {"rank": 35, "name": "如何看待 KPL 秋季赛常规赛收官之战武汉 eStar 3:2 重庆狼队？", "count": "6 万热度", "link": "https:\\\\www.zhihu.com\\question\\502290497", "desc": "\"},\"imageArea\":{\"url\":\"https:\\u002F\\u002Fpic3.zhimg.com\\u002F80\\u002Fv2-eeec230ed8130672a2a38bde9092d013_720w.jpg"}, {"rank": 36, "name": "你的家乡有哪些「永远停留在记忆深处」的美景吗？", "count": "6 万热度", "link": "https:\\\\www.zhihu.com\\question\\500697947", "desc": "\"},\"imageArea\":{\"url\":\"https:\\u002F\\u002Fpic2.zhimg.com\\u002F80\\u002Fv2-15dfb649b342aa1b5a0de0cfa7c1c136_720w.jpg"}, {"rank": 37, "name": "有没有微信置顶的神仙文案？", "count": "6 万热度", "link": "https:\\\\www.zhihu.com\\question\\480993045", "desc": "\"},\"imageArea\":{\"url\":\"https:\\u002F\\u002Fpic3.zhimg.com\\u002Fv2-58cfe1f02ebb3befc867505b09fbea03_720w.jpg"}, {"rank": 38, "name": "电视剧《女心理师》有哪些值得关注的细节？", "count": "6 万热度", "link": "https:\\\\www.zhihu.com\\question\\500930541", "desc": "讲述贺顿（杨紫饰）通过心理咨询，解析多位来访者心理问题的成因，在相应的心理治疗中，帮助他们走出过往的心理阴霾，重新拥抱生活的动人故事。这一路上，贺顿和电台主播钱开逸（井柏然饰）、意外结识的好友叶家辉（王嘉饰）、以及闺蜜汤莉莉（菅纫姿饰）一起，在一系列笑与泪交织的经历中疗愈他人也收获了自愈。"}, {"rank": 39, "name": "怎样在一个月时间顺利过六级？", "count": "6 万热度", "link": "https:\\\\www.zhihu.com\\question\\30033713", "desc": "\"},\"imageArea\":{\"url\":\"https:\\u002F\\u002Fpic1.zhimg.com\\u002F80\\u002Fv2-4bca4051db418623a619fee30b847af5_720w.png"}, {"rank": 40, "name": "室友总想借我的 Apple pencil 怎么拒绝？", "count": "6 万热度", "link": "https:\\\\www.zhihu.com\\question\\498943448", "desc": "新买一个 Apple pencil，感觉她比我还着急用，总问我到了没，借我用用，到了给我玩玩，让我用用学习之类的，救命 咋办～ 怎么拒绝？求救"}, {"rank": 41, "name": "什么好物能够代表你的家乡特色？", "count": "6 万热度", "link": "https:\\\\www.zhihu.com\\question\\498203374", "desc": "一座「城」，容纳了一座城的好物。是什么让你的家乡变得独特？是什么代表了你的家乡？ 参与要求： 发布 200 字以上优质内容，经审核通过即可领取红包。每个问题提供价值 1888 元现金红包，先到先得、发完为止。 活动时间： 2021 年 11 月 29 日 -2021 年 12 月 20 日 站内搜索「城市好物」或点击卡片进入活动主会场，瓜分更多现金红包：城市好物集"}, {"rank": 42, "name": "如果让计算机不使用操作系统做服务器性能上是否会更有优势?", "count": "6 万热度", "link": "https:\\\\www.zhihu.com\\question\\500261279", "desc": "这是我最近思考的一个问题，如果写一个裸机跑的实模式的系统程序，该程序只提供 web 或者数据库之内的其中一项服务，且一台服务器只提供一项服务 (只跑一个程序)，先不考虑安全之类的问题，如果让计算机这样的形式提供服务，性能上是否会更具有优势?"}, {"rank": 43, "name": "小婴儿都有哪些奇怪的睡姿？", "count": "6 万热度", "link": "https:\\\\www.zhihu.com\\question\\407373958", "desc": "晒出你们小宝宝的睡姿吧！另外需要对小婴儿的睡姿进行干预吗？"}, {"rank": 44, "name": "如何分析 2021 亚太杯数学建模 ABC 题？思路代码是什么？", "count": "6 万热度", "link": "https:\\\\www.zhihu.com\\question\\500654919", "desc": "希望大佬来帮助一下"}, {"rank": 45, "name": "汉语语法在哪些方面过于繁琐？", "count": "6 万热度", "link": "https:\\\\www.zhihu.com\\question\\23554440", "desc": "最近学日语觉得有些语法真是繁琐。反过来看汉语，作为中国人本身，可能没有意识到一些语法比较烦，那研究汉语或者外国人，对于汉语语法有哪些繁琐得让人想吐槽的地方？"}, {"rank": 46, "name": "什么样的人才能做好价值投资？", "count": "6 万热度", "link": "https:\\\\www.zhihu.com\\question\\491550206", "desc": "\"},\"imageArea\":{\"url\":\"https:\\u002F\\u002Fpic3.zhimg.com\\u002F80\\u002Fv2-097f53826cef10e7ec97684cecf776b6_720w.png"}, {"rank": 47, "name": "如果现在的游戏把体力系统去掉会发生什么？", "count": "6 万热度", "link": "https:\\\\www.zhihu.com\\question\\38372391", "desc": "体力系统是大家用来控制用户游戏进度、节奏，缩减用户差距的一套行之有效的规则，那么如果在当前环境下去掉这套规则会怎样呢？ --- 抱歉，问题没有主语是我的不对，题中的疑问的主体也确实是偏向于手游这一块的。 在这里感谢每一个回答的朋友，感谢你们的热心，在这里根据大家的回答再做一点补充，没有跟发行和渠道的人打过太多正经交道，不知道他们是怎么看这一块的，但是说实话 @猴与花果山 的回答在下还是有点理解不了。 关于游戏类型和游戏平台的补充。如果说我想做的是一个 RTS 、 MOBA 、 TCG 之类的竞技游戏，那么我不会提出这么一个问题，把玩游戏比做吃饭的话，竞技游戏锅里的饭有多少很大程度决定于有多少人在玩，不会太快出现对于游戏内容消耗的焦虑。游戏机、 PC 平台的大部分非竞技类游戏，采取的做法是一次性把游戏内容卖给你（不要脸的就半成品开卖后面内容 DLC），消耗的问题抛给了玩家，也不存在控制一说了。所以这两块的东西虽好，但也没太多参考价值。 还有朋友提到的创造型游戏，这个东西不能只看到一个 MC 在各大平台火的不行（然而也是买断模式 -3-）另有几个成功的游戏也各有特点，各个大厂都在跟风，还有多少跟风的小朋友死在成功的路上了想过没，题主虽然有点自命不凡，但也没觉得能 hold 住这么一个项目。 看大家的说法也想了很多，题主也明白体力系统不管是对设计者还是消费者来说都能带来很多好处，会提出这个问题是因为潜意识里觉得这个东西还是有毛病的，那么大家觉得这个体力系统会对游戏带来怎样的负面影响呢？"}, {"rank": 48, "name": "为什么 iPhone13 发布后，网上说它屏幕伤眼的越来越多？", "count": "6 万热度", "link": "https:\\\\www.zhihu.com\\question\\497239140", "desc": "从 2017 年 iphonex 的第一块 oled 屏幕发布至今，几十亿部 oled 的 iPhone 卖出去了，为什么直到 2021 年的 13，网上突然铺天盖地的 oled 屏幕「伤眼」袭来？ 之前的难道不伤了么？"}, {"rank": 49, "name": "如何看待游戏《原神》新 boss 黄金王兽？", "count": "6 万热度", "link": "https:\\\\www.zhihu.com\\question\\501311427", "desc": "感觉这玩意儿好猛啊。钟离玩家终于回忆起了被怪物支配的恐惧，以及神像被榨干的屈辱。"}, {"rank": 50, "name": "励志文案短句有哪些？", "count": "6 万热度", "link": "https:\\\\www.zhihu.com\\question\\494054921", "desc": "\"},\"imageArea\":{\"url\":\"https:\\u002F\\u002Fpic2.zhimg.com\\u002F50\\u002Fv2-d822a823bcde790aa5dc71f686eba591_b.jpg"}], "name": "知乎热搜"}, "xiaohongshu": {"tops": [{"rank": 1, "name": "冬日热汗打卡", "count": "558w", "link": "https://creator.xiaohongshu.com/topic?topic=61889b98b2c7560001ac5c40&page_entrance_type=冬日热汗打卡"}, {"rank": 2, "name": "安利你的国货好物", "count": "546w", "link": "https://creator.xiaohongshu.com/topic?topic=5be55473d111a500019287c5&page_entrance_type=安利你的国货好物"}, {"rank": 3, "name": "是时候叠穿了", "count": "531w", "link": "https://creator.xiaohongshu.com/topic?topic=619259583c7dc80001483d2f&page_entrance_type=是时候叠穿了"}, {"rank": 4, "name": "全家投壶挑战", "count": "527w", "link": "https://creator.xiaohongshu.com/topic?topic=618a75994460690001db140a&page_entrance_type=全家投壶挑战"}, {"rank": 5, "name": "小红书冰雪季", "count": "512w", "link": "https://creator.xiaohongshu.com/topic?topic=617bc440110ff300018c805f&page_entrance_type=小红书冰雪季"}, {"rank": 6, "name": "投影仪的100种玩法", "count": "503w", "link": "https://creator.xiaohongshu.com/topic?topic=619b4860233c6100015c1854&page_entrance_type=投影仪的100种玩法"}, {"rank": 7, "name": "真人化妆小游戏", "count": "491w", "link": "https://creator.xiaohongshu.com/topic?topic=619b4d88b7c200000156b0d1&page_entrance_type=真人化妆小游戏"}, {"rank": 8, "name": "换装小游戏真人版", "count": "467w", "link": "https://creator.xiaohongshu.com/topic?topic=5c54841ab832cf000182c03f&page_entrance_type=换装小游戏真人版"}, {"rank": 9, "name": "玲娜贝儿灵感妆", "count": "459w", "link": "https://creator.xiaohongshu.com/topic?topic=618b5f7b92c08200018b1acb&page_entrance_type=玲娜贝儿灵感妆"}, {"rank": 10, "name": "华流国风妆造", "count": "446w", "link": "https://creator.xiaohongshu.com/topic?topic=61952237eeb6d400013c2d49&page_entrance_type=华流国风妆造"}, {"rank": 11, "name": "冬天第一杯热红酒", "count": "438w", "link": "https://creator.xiaohongshu.com/topic?topic=61780c8e85f6270001227730&page_entrance_type=冬天第一杯热红酒"}, {"rank": 12, "name": "给肠道减负的健康餐", "count": "429w", "link": "https://creator.xiaohongshu.com/topic?topic=5be7cec1aead090001f4f197&page_entrance_type=给肠道减负的健康餐"}, {"rank": 13, "name": "健身人的光剑变装", "count": "411w", "link": "https://creator.xiaohongshu.com/topic?topic=61878a6d5c090c00013e3a22&page_entrance_type=健身人的光剑变装"}, {"rank": 14, "name": "你经历过最孤独的一件事", "count": "393w", "link": "https://creator.xiaohongshu.com/topic?topic=5c349378517cd9000185bf67&page_entrance_type=你经历过最孤独的一件事"}, {"rank": 15, "name": "富家千金的秋冬穿搭", "count": "385w", "link": "https://creator.xiaohongshu.com/topic?topic=610eb38eac3dda0001e0da94&page_entrance_type=富家千金的秋冬穿搭"}, {"rank": 16, "name": "冬季暖男穿搭", "count": "364w", "link": "https://creator.xiaohongshu.com/topic?topic=5da585751e26fd00015b76cb&page_entrance_type=冬季暖男穿搭"}, {"rank": 17, "name": "圣诞送礼指南", "count": "341w", "link": "https://creator.xiaohongshu.com/topic?topic=5c11e4b824e1fc0001546391&page_entrance_type=圣诞送礼指南"}, {"rank": 18, "name": "城市里的宝藏小店", "count": "328w", "link": "https://creator.xiaohongshu.com/topic?topic=5fbb2d106759d10001932f09&page_entrance_type=城市里的宝藏小店"}, {"rank": 19, "name": "圣诞风猫窝DIY", "count": "299w", "link": "https://creator.xiaohongshu.com/topic?topic=5bf2cc7be6149c000119fc92&page_entrance_type=圣诞风猫窝DIY"}, {"rank": 20, "name": "秋招血泪史复盘", "count": "283w", "link": "https://creator.xiaohongshu.com/topic?topic=5bf57771e6149c00014bac93&page_entrance_type=秋招血泪史复盘"}, {"rank": 21, "name": "秋冬身体保湿怎么做", "count": "266w", "link": "https://creator.xiaohongshu.com/topic?topic=5a438d8f800086066171f55d&page_entrance_type=秋冬身体保湿怎么做"}, {"rank": 22, "name": "养宠物的暖心瞬间", "count": "248w", "link": "https://creator.xiaohongshu.com/topic?topic=5a438d8f800086066171f5d5&page_entrance_type=养宠物的暖心瞬间"}, {"rank": 23, "name": "圣诞风饮品打卡", "count": "236w", "link": "https://creator.xiaohongshu.com/topic?topic=5fd19bf64c03640001cbb628&page_entrance_type=圣诞风饮品打卡"}, {"rank": 24, "name": "留学那些事", "count": "219w", "link": "https://creator.xiaohongshu.com/topic?topic=5abb2adeec9d131cae542d99&page_entrance_type=留学那些事"}, {"rank": 25, "name": "画个小人和波吉排排坐", "count": "193w", "link": "https://creator.xiaohongshu.com/topic?topic=613ed8bfd509330001a9f9b8&page_entrance_type=画个小人和波吉排排坐"}, {"rank": 26, "name": "秋冬微醺红酒妆", "count": "171w", "link": "https://creator.xiaohongshu.com/topic?topic=5d78e9d66b82c90001e1c13f&page_entrance_type=秋冬微醺红酒妆"}, {"rank": 27, "name": "玲娜贝儿周边拿捏了", "count": "159w", "link": "https://creator.xiaohongshu.com/topic?topic=6143eaf3eb38de0001d62657&page_entrance_type=玲娜贝儿周边拿捏了"}, {"rank": 28, "name": "考研政治冲刺攻略", "count": "141w", "link": "https://creator.xiaohongshu.com/topic?topic=5d5168907b5a5c000170f0fe&page_entrance_type=考研政治冲刺攻略"}, {"rank": 29, "name": "对家暴说No", "count": "135w", "link": "https://creator.xiaohongshu.com/topic?topic=5e775afb3f10100001423b35&page_entrance_type=对家暴说No"}, {"rank": 30, "name": "吃货的花束", "count": "116w", "link": "https://creator.xiaohongshu.com/topic?topic=60baf9f8412d270001118072&page_entrance_type=吃货的花束"}], "name": "小红书本周热点"}}, "datetime": "2021年11月30日 09:11:54"}